{"nhits": 102, "parameters": {"dataset": ["arpege-05-sp1_sp2"], "timezone": "UTC", "rows": 10000, "start": 0, "format": "json", "geofilter.distance": ["47.322047,5.04148,40000"], "facet": ["forecast"]}, "records": [{"datasetid": "arpege-05-sp1_sp2", "recordid": "arpege_05_sp1_sp2_lastgrib20-2081143", "fields": {"2_metre_dewpoint_temperature": -3.426305999999954, "downward_short_wave_radiation_flux": 156672.0, "2_metre_temperature": 0.33510700000005045, "dist": "20032.1688823", "temperature": 0.1300899999999956, "minimum_temperature_at_2_metres": -0.492040999999972, "timestamp": "2021-02-15T00:00:00+00:00", "v_component_of_wind_gust": 10.016205, "total_water_precipitation": 0.021484, "relative_humidity": 73.432663, "u_component_of_wind_gust": -1.109055, "wind_speed_gust": 10.076233, "position": [47.5, 5.0], "forecast": "2021-02-15T09:00:00+00:00", "maximum_temperature_at_2_metres": 0.3284550000000195, "total_cloud_cover": 100.0, "downward_long_wave_radiation_flux": 8900446.0}, "geometry": {"type": "Point", "coordinates": [5.0, 47.5]}, "record_timestamp": "2021-02-15T00:00:00+00:00"}, {"datasetid": "arpege-05-sp1_sp2", "recordid": "arpege_05_sp1_sp2_lastgrib20-2081147", "fields": {"2_metre_dewpoint_temperature": 0.7017460000000142, "downward_short_wave_radiation_flux": 3438592.0, "2_metre_temperature": 1.7623540000000162, "dist": "20032.1688823", "temperature": 1.165063000000032, "minimum_temperature_at_2_metres": 1.7436770000000479, "timestamp": "2021-02-15T00:00:00+00:00", "v_component_of_wind_gust": 7.744675, "total_water_precipitation": 0.636719, "relative_humidity": 92.629265, "u_component_of_wind_gust": -0.293808, "wind_speed_gust": 7.74342, "position": [47.5, 5.0], "forecast": "2021-02-15T21:00:00+00:00", "maximum_temperature_at_2_metres": 2.192346000000043, "total_cloud_cover": 96.5, "downward_long_wave_radiation_flux": 21688072.0}, "geometry": {"type": "Point", "coordinates": [5.0, 47.5]}, "record_timestamp": "2021-02-15T00:00:00+00:00"}, {"datasetid": "arpege-05-sp1_sp2", "recordid": "arpege_05_sp1_sp2_lastgrib20-2081151", "fields": {"2_metre_dewpoint_temperature": 3.0314580000000433, "downward_short_wave_radiation_flux": 3959808.0, "2_metre_temperature": 3.437280000000044, "dist": "20032.1688823", "temperature": 3.5029240000000073, "minimum_temperature_at_2_metres": 1.9751530000000344, "timestamp": "2021-02-15T00:00:00+00:00", "v_component_of_wind_gust": 8.494293, "total_water_precipitation": 0.753906, "relative_humidity": 97.139793, "u_component_of_wind_gust": -1.116638, "wind_speed_gust": 8.548315, "position": [47.5, 5.0], "forecast": "2021-02-16T09:00:00+00:00", "maximum_temperature_at_2_metres": 3.434045000000026, "total_cloud_cover": 87.0, "downward_long_wave_radiation_flux": 34238284.0}, "geometry": {"type": "Point", "coordinates": [5.0, 47.5]}, "record_timestamp": "2021-02-15T00:00:00+00:00"}, {"datasetid": "arpege-05-sp1_sp2", "recordid": "arpege_05_sp1_sp2_lastgrib20-2081169", "fields": {"2_metre_dewpoint_temperature": 7.759973000000002, "downward_short_wave_radiation_flux": 27414528.0, "2_metre_temperature": 9.503076000000021, "dist": "20032.1688823", "temperature": 9.26391000000001, "minimum_temperature_at_2_metres": 2.794885000000022, "timestamp": "2021-02-15T00:00:00+00:00", "v_component_of_wind_gust": 10.561844, "total_water_precipitation": 2.523438, "relative_humidity": 88.845009, "u_component_of_wind_gust": -0.932632, "wind_speed_gust": 10.611752, "position": [47.5, 5.0], "forecast": "2021-02-18T15:00:00+00:00", "maximum_temperature_at_2_metres": 9.843011000000047, "total_cloud_cover": 100.0, "downward_long_wave_radiation_flux": 90459936.0}, "geometry": {"type": "Point", "coordinates": [5.0, 47.5]}, "record_timestamp": "2021-02-15T00:00:00+00:00"}, {"datasetid": "arpege-05-sp1_sp2", "recordid": "arpege_05_sp1_sp2_lastgrib20-2081145", "fields": {"2_metre_dewpoint_temperature": 1.5020390000000248, "downward_short_wave_radiation_flux": 3331584.0, "2_metre_temperature": 3.1171510000000353, "dist": "20032.1688823", "temperature": 2.817102000000034, "minimum_temperature_at_2_metres": 2.1994260000000168, "timestamp": "2021-02-15T00:00:00+00:00", "v_component_of_wind_gust": 6.909271, "total_water_precipitation": 0.277344, "relative_humidity": 89.070183, "u_component_of_wind_gust": -0.306427, "wind_speed_gust": 6.910124, "position": [47.5, 5.0], "forecast": "2021-02-15T15:00:00+00:00", "maximum_temperature_at_2_metres": 3.6243840000000205, "total_cloud_cover": 99.0, "downward_long_wave_radiation_flux": 15361051.0}, "geometry": {"type": "Point", "coordinates": [5.0, 47.5]}, "record_timestamp": "2021-02-15T00:00:00+00:00"}, {"datasetid": "arpege-05-sp1_sp2", "recordid": "arpege_05_sp1_sp2_lastgrib20-2081153", "fields": {"2_metre_dewpoint_temperature": 6.460260000000005, "downward_short_wave_radiation_flux": 11642880.0, "2_metre_temperature": 8.199060000000031, "dist": "20032.1688823", "temperature": 8.119348000000002, "minimum_temperature_at_2_metres": 7.728052000000048, "timestamp": "2021-02-15T00:00:00+00:00", "v_component_of_wind_gust": 8.170654, "total_water_precipitation": 0.757813, "relative_humidity": 88.755302, "u_component_of_wind_gust": -0.832535, "wind_speed_gust": 8.21578, "position": [47.5, 5.0], "forecast": "2021-02-16T15:00:00+00:00", "maximum_temperature_at_2_metres": 8.471033000000034, "total_cloud_cover": 100.0, "downward_long_wave_radiation_flux": 40198192.0}, "geometry": {"type": "Point", "coordinates": [5.0, 47.5]}, "record_timestamp": "2021-02-15T00:00:00+00:00"}, {"datasetid": "arpege-05-sp1_sp2", "recordid": "arpege_05_sp1_sp2_lastgrib20-2081160", "fields": {"2_metre_dewpoint_temperature": 4.936792000000025, "downward_short_wave_radiation_flux": 17606656.0, "2_metre_temperature": 8.642847000000017, "dist": "20032.1688823", "temperature": 10.692621000000031, "minimum_temperature_at_2_metres": 5.019830000000013, "timestamp": "2021-02-15T00:00:00+00:00", "v_component_of_wind_gust": 1.856247, "total_water_precipitation": 2.476563, "relative_humidity": 77.531517, "u_component_of_wind_gust": 4.397263, "wind_speed_gust": 4.77849, "position": [47.5, 5.0], "forecast": "2021-02-17T12:00:00+00:00", "maximum_temperature_at_2_metres": 8.659113000000048, "total_cloud_cover": 49.0, "downward_long_wave_radiation_flux": 62661120.0}, "geometry": {"type": "Point", "coordinates": [5.0, 47.5]}, "record_timestamp": "2021-02-15T00:00:00+00:00"}, {"datasetid": "arpege-05-sp1_sp2", "recordid": "arpege_05_sp1_sp2_lastgrib20-2081162", "fields": {"2_metre_dewpoint_temperature": 4.478174000000024, "downward_short_wave_radiation_flux": 22753280.0, "2_metre_temperature": 4.656701999999996, "dist": "20032.1688823", "temperature": 3.7137390000000323, "minimum_temperature_at_2_metres": 4.637902999999994, "timestamp": "2021-02-15T00:00:00+00:00", "v_component_of_wind_gust": 3.769913, "total_water_precipitation": 2.476563, "relative_humidity": 98.797279, "u_component_of_wind_gust": -1.189301, "wind_speed_gust": 3.962252, "position": [47.5, 5.0], "forecast": "2021-02-17T18:00:00+00:00", "maximum_temperature_at_2_metres": 9.374048000000016, "total_cloud_cover": 88.0, "downward_long_wave_radiation_flux": 68377120.0}, "geometry": {"type": "Point", "coordinates": [5.0, 47.5]}, "record_timestamp": "2021-02-15T00:00:00+00:00"}, {"datasetid": "arpege-05-sp1_sp2", "recordid": "arpege_05_sp1_sp2_lastgrib20-2081171", "fields": {"2_metre_dewpoint_temperature": 4.038416000000041, "downward_short_wave_radiation_flux": 27484160.0, "2_metre_temperature": 5.638269000000037, "dist": "20032.1688823", "temperature": 4.98195800000002, "minimum_temperature_at_2_metres": 2.7710820000000354, "timestamp": "2021-02-15T00:00:00+00:00", "v_component_of_wind_gust": -0.526184, "total_water_precipitation": 4.976563, "relative_humidity": 89.431442, "u_component_of_wind_gust": 11.005646, "wind_speed_gust": 11.026268, "position": [47.5, 5.0], "forecast": "2021-02-18T21:00:00+00:00", "maximum_temperature_at_2_metres": 9.81832300000002, "total_cloud_cover": 1.0, "downward_long_wave_radiation_flux": 97405520.0}, "geometry": {"type": "Point", "coordinates": [5.0, 47.5]}, "record_timestamp": "2021-02-15T00:00:00+00:00"}, {"datasetid": "arpege-05-sp1_sp2", "recordid": "arpege_05_sp1_sp2_lastgrib20-2081140", "fields": {"2_metre_dewpoint_temperature": -2.3139400000000023, "2_metre_temperature": -0.8304200000000037, "dist": "20032.1688823", "temperature": -0.6786249999999541, "timestamp": "2021-02-15T00:00:00+00:00", "forecast": "2021-02-15T00:00:00+00:00", "relative_humidity": 88.385483, "position": [47.5, 5.0], "total_cloud_cover": 100.0}, "geometry": {"type": "Point", "coordinates": [5.0, 47.5]}, "record_timestamp": "2021-02-15T00:00:00+00:00"}, {"datasetid": "arpege-05-sp1_sp2", "recordid": "arpege_05_sp1_sp2_lastgrib20-2081142", "fields": {"2_metre_dewpoint_temperature": -3.5473389999999654, "downward_short_wave_radiation_flux": 0.0, "2_metre_temperature": -0.5350399999999809, "dist": "20032.1688823", "temperature": -0.9794069999999806, "minimum_temperature_at_2_metres": -0.7752439999999865, "timestamp": "2021-02-15T00:00:00+00:00", "v_component_of_wind_gust": 9.786652, "total_water_precipitation": 0.005859, "relative_humidity": 77.738014, "u_component_of_wind_gust": -1.387527, "wind_speed_gust": 9.884459, "position": [47.5, 5.0], "forecast": "2021-02-15T06:00:00+00:00", "maximum_temperature_at_2_metres": -0.4217589999999518, "total_cloud_cover": 100.0, "downward_long_wave_radiation_flux": 5776073.0}, "geometry": {"type": "Point", "coordinates": [5.0, 47.5]}, "record_timestamp": "2021-02-15T00:00:00+00:00"}, {"datasetid": "arpege-05-sp1_sp2", "recordid": "arpege_05_sp1_sp2_lastgrib20-2081164", "fields": {"2_metre_dewpoint_temperature": 0.35103800000001684, "downward_short_wave_radiation_flux": 22753280.0, "2_metre_temperature": 0.36324500000000626, "dist": "20032.1688823", "temperature": -0.48203099999994947, "minimum_temperature_at_2_metres": 0.3496030000000019, "timestamp": "2021-02-15T00:00:00+00:00", "v_component_of_wind_gust": 1.27594, "total_water_precipitation": 2.476563, "relative_humidity": 99.960823, "u_component_of_wind_gust": 0.306564, "wind_speed_gust": 1.304549, "position": [47.5, 5.0], "forecast": "2021-02-18T00:00:00+00:00", "maximum_temperature_at_2_metres": 0.8846070000000168, "total_cloud_cover": 100.0, "downward_long_wave_radiation_flux": 73858736.0}, "geometry": {"type": "Point", "coordinates": [5.0, 47.5]}, "record_timestamp": "2021-02-15T00:00:00+00:00"}, {"datasetid": "arpege-05-sp1_sp2", "recordid": "arpege_05_sp1_sp2_lastgrib20-2081172", "fields": {"2_metre_dewpoint_temperature": 1.6704349999999977, "downward_short_wave_radiation_flux": 27484160.0, "2_metre_temperature": 2.3839360000000056, "dist": "20032.1688823", "temperature": 1.28731700000003, "minimum_temperature_at_2_metres": 2.391565000000014, "timestamp": "2021-02-15T00:00:00+00:00", "v_component_of_wind_gust": 0.849991, "total_water_precipitation": 4.984375, "relative_humidity": 94.996361, "u_component_of_wind_gust": 4.663589, "wind_speed_gust": 4.742654, "position": [47.5, 5.0], "forecast": "2021-02-19T00:00:00+00:00", "maximum_temperature_at_2_metres": 9.807642000000044, "total_cloud_cover": 85.0, "downward_long_wave_radiation_flux": 99990064.0}, "geometry": {"type": "Point", "coordinates": [5.0, 47.5]}, "record_timestamp": "2021-02-15T00:00:00+00:00"}, {"datasetid": "arpege-05-sp1_sp2", "recordid": "arpege_05_sp1_sp2_lastgrib20-2081150", "fields": {"2_metre_dewpoint_temperature": 1.6440060000000472, "downward_short_wave_radiation_flux": 3438592.0, "2_metre_temperature": 1.8747800000000439, "dist": "20032.1688823", "temperature": 1.3199710000000096, "minimum_temperature_at_2_metres": 1.7652830000000108, "timestamp": "2021-02-15T00:00:00+00:00", "v_component_of_wind_gust": 8.426224, "total_water_precipitation": 0.753906, "relative_humidity": 98.461678, "u_component_of_wind_gust": -1.218262, "wind_speed_gust": 8.530411, "position": [47.5, 5.0], "forecast": "2021-02-16T06:00:00+00:00", "maximum_temperature_at_2_metres": 1.9177490000000148, "total_cloud_cover": 100.0, "downward_long_wave_radiation_flux": 31057812.0}, "geometry": {"type": "Point", "coordinates": [5.0, 47.5]}, "record_timestamp": "2021-02-15T00:00:00+00:00"}, {"datasetid": "arpege-05-sp1_sp2", "recordid": "arpege_05_sp1_sp2_lastgrib20-2081157", "fields": {"2_metre_dewpoint_temperature": 5.432703000000004, "downward_short_wave_radiation_flux": 12152832.0, "2_metre_temperature": 5.941309000000047, "dist": "20032.1688823", "temperature": 5.271356000000026, "minimum_temperature_at_2_metres": 5.923730000000035, "timestamp": "2021-02-15T00:00:00+00:00", "v_component_of_wind_gust": 1.096832, "total_water_precipitation": 2.476563, "relative_humidity": 96.665337, "u_component_of_wind_gust": 6.579315, "wind_speed_gust": 6.661902, "position": [47.5, 5.0], "forecast": "2021-02-17T03:00:00+00:00", "maximum_temperature_at_2_metres": 6.604425000000049, "total_cloud_cover": 96.0, "downward_long_wave_radiation_flux": 53803636.0}, "geometry": {"type": "Point", "coordinates": [5.0, 47.5]}, "record_timestamp": "2021-02-15T00:00:00+00:00"}, {"datasetid": "arpege-05-sp1_sp2", "recordid": "arpege_05_sp1_sp2_lastgrib20-2081146", "fields": {"2_metre_dewpoint_temperature": 1.0175420000000486, "downward_short_wave_radiation_flux": 3438592.0, "2_metre_temperature": 2.1745240000000194, "dist": "20032.1688823", "temperature": 1.5451290000000313, "minimum_temperature_at_2_metres": 2.149133000000006, "timestamp": "2021-02-15T00:00:00+00:00", "v_component_of_wind_gust": 8.145905, "total_water_precipitation": 0.636719, "relative_humidity": 92.04274, "u_component_of_wind_gust": 0.329422, "wind_speed_gust": 8.173265, "position": [47.5, 5.0], "forecast": "2021-02-15T18:00:00+00:00", "maximum_temperature_at_2_metres": 2.9902590000000373, "total_cloud_cover": 98.0, "downward_long_wave_radiation_flux": 18637760.0}, "geometry": {"type": "Point", "coordinates": [5.0, 47.5]}, "record_timestamp": "2021-02-15T00:00:00+00:00"}, {"datasetid": "arpege-05-sp1_sp2", "recordid": "arpege_05_sp1_sp2_lastgrib20-2081148", "fields": {"2_metre_dewpoint_temperature": 1.0100950000000353, "downward_short_wave_radiation_flux": 3438592.0, "2_metre_temperature": 1.9520200000000045, "dist": "20032.1688823", "temperature": 1.4677670000000376, "minimum_temperature_at_2_metres": 1.407098000000019, "timestamp": "2021-02-15T00:00:00+00:00", "v_component_of_wind_gust": 6.369751, "total_water_precipitation": 0.710938, "relative_humidity": 93.329651, "u_component_of_wind_gust": -0.527649, "wind_speed_gust": 6.39942, "position": [47.5, 5.0], "forecast": "2021-02-16T00:00:00+00:00", "maximum_temperature_at_2_metres": 1.9608090000000402, "total_cloud_cover": 98.5, "downward_long_wave_radiation_flux": 24978568.0}, "geometry": {"type": "Point", "coordinates": [5.0, 47.5]}, "record_timestamp": "2021-02-15T00:00:00+00:00"}, {"datasetid": "arpege-05-sp1_sp2", "recordid": "arpege_05_sp1_sp2_lastgrib20-2081152", "fields": {"2_metre_dewpoint_temperature": 5.425745000000006, "downward_short_wave_radiation_flux": 7950336.0, "2_metre_temperature": 7.659235000000024, "dist": "20032.1688823", "temperature": 8.654321000000039, "minimum_temperature_at_2_metres": 3.5552000000000135, "timestamp": "2021-02-15T00:00:00+00:00", "v_component_of_wind_gust": 7.81813, "total_water_precipitation": 0.757813, "relative_humidity": 85.697884, "u_component_of_wind_gust": -1.470688, "wind_speed_gust": 7.951542, "position": [47.5, 5.0], "forecast": "2021-02-16T12:00:00+00:00", "maximum_temperature_at_2_metres": 7.67891800000001, "total_cloud_cover": 84.5, "downward_long_wave_radiation_flux": 37251800.0}, "geometry": {"type": "Point", "coordinates": [5.0, 47.5]}, "record_timestamp": "2021-02-15T00:00:00+00:00"}, {"datasetid": "arpege-05-sp1_sp2", "recordid": "arpege_05_sp1_sp2_lastgrib20-2081155", "fields": {"2_metre_dewpoint_temperature": 5.52266800000001, "downward_short_wave_radiation_flux": 12151808.0, "2_metre_temperature": 6.497064000000023, "dist": "20032.1688823", "temperature": 5.234491000000048, "minimum_temperature_at_2_metres": 4.704094999999995, "timestamp": "2021-02-15T00:00:00+00:00", "v_component_of_wind_gust": 4.237564, "total_water_precipitation": 0.886719, "relative_humidity": 93.474167, "u_component_of_wind_gust": 6.863052, "wind_speed_gust": 8.057429, "position": [47.5, 5.0], "forecast": "2021-02-16T21:00:00+00:00", "maximum_temperature_at_2_metres": 6.499780000000044, "total_cloud_cover": 99.5, "downward_long_wave_radiation_flux": 46479904.0}, "geometry": {"type": "Point", "coordinates": [5.0, 47.5]}, "record_timestamp": "2021-02-15T00:00:00+00:00"}, {"datasetid": "arpege-05-sp1_sp2", "recordid": "arpege_05_sp1_sp2_lastgrib20-2081156", "fields": {"2_metre_dewpoint_temperature": 5.935266000000013, "downward_short_wave_radiation_flux": 12152832.0, "2_metre_temperature": 6.377770999999996, "dist": "20032.1688823", "temperature": 5.616815000000031, "minimum_temperature_at_2_metres": 6.350427000000025, "timestamp": "2021-02-15T00:00:00+00:00", "v_component_of_wind_gust": 2.853378, "total_water_precipitation": 2.460938, "relative_humidity": 97.010025, "u_component_of_wind_gust": 5.343384, "wind_speed_gust": 6.034594, "position": [47.5, 5.0], "forecast": "2021-02-17T00:00:00+00:00", "maximum_temperature_at_2_metres": 6.759058000000039, "total_cloud_cover": 97.0, "downward_long_wave_radiation_flux": 50173128.0}, "geometry": {"type": "Point", "coordinates": [5.0, 47.5]}, "record_timestamp": "2021-02-15T00:00:00+00:00"}, {"datasetid": "arpege-05-sp1_sp2", "recordid": "arpege_05_sp1_sp2_lastgrib20-2081166", "fields": {"2_metre_dewpoint_temperature": 2.2343380000000366, "downward_short_wave_radiation_flux": 22753280.0, "2_metre_temperature": 2.548761000000013, "dist": "20032.1688823", "temperature": 2.209924000000001, "minimum_temperature_at_2_metres": 0.828394000000003, "timestamp": "2021-02-15T00:00:00+00:00", "v_component_of_wind_gust": 6.508789, "total_water_precipitation": 2.492188, "relative_humidity": 97.730637, "u_component_of_wind_gust": -2.407761, "wind_speed_gust": 6.924205, "position": [47.5, 5.0], "forecast": "2021-02-18T06:00:00+00:00", "maximum_temperature_at_2_metres": 2.549890000000005, "total_cloud_cover": 91.5, "downward_long_wave_radiation_flux": 80644368.0}, "geometry": {"type": "Point", "coordinates": [5.0, 47.5]}, "record_timestamp": "2021-02-15T00:00:00+00:00"}, {"datasetid": "arpege-05-sp1_sp2", "recordid": "arpege_05_sp1_sp2_lastgrib20-2081167", "fields": {"2_metre_dewpoint_temperature": 4.169550000000015, "downward_short_wave_radiation_flux": 23246848.0, "2_metre_temperature": 4.655327999999997, "dist": "20032.1688823", "temperature": 4.618188000000032, "minimum_temperature_at_2_metres": 2.753015000000005, "timestamp": "2021-02-15T00:00:00+00:00", "v_component_of_wind_gust": 9.048523, "total_water_precipitation": 2.492188, "relative_humidity": 96.588791, "u_component_of_wind_gust": -1.652344, "wind_speed_gust": 9.193254, "position": [47.5, 5.0], "forecast": "2021-02-18T09:00:00+00:00", "maximum_temperature_at_2_metres": 4.657831000000044, "total_cloud_cover": 100.0, "downward_long_wave_radiation_flux": 83837728.0}, "geometry": {"type": "Point", "coordinates": [5.0, 47.5]}, "record_timestamp": "2021-02-15T00:00:00+00:00"}, {"datasetid": "arpege-05-sp1_sp2", "recordid": "arpege_05_sp1_sp2_lastgrib20-2081170", "fields": {"2_metre_dewpoint_temperature": 6.1679320000000075, "downward_short_wave_radiation_flux": 27486208.0, "2_metre_temperature": 7.582819000000029, "dist": "20032.1688823", "temperature": 6.77749, "minimum_temperature_at_2_metres": 2.806299000000024, "timestamp": "2021-02-15T00:00:00+00:00", "v_component_of_wind_gust": 8.189148, "total_water_precipitation": 4.75, "relative_humidity": 90.863831, "u_component_of_wind_gust": 9.102097, "wind_speed_gust": 12.241389, "position": [47.5, 5.0], "forecast": "2021-02-18T18:00:00+00:00", "maximum_temperature_at_2_metres": 9.85323500000004, "total_cloud_cover": 100.0, "downward_long_wave_radiation_flux": 94028512.0}, "geometry": {"type": "Point", "coordinates": [5.0, 47.5]}, "record_timestamp": "2021-02-15T00:00:00+00:00"}, {"datasetid": "arpege-05-sp1_sp2", "recordid": "arpege_05_sp1_sp2_lastgrib20-2081161", "fields": {"2_metre_dewpoint_temperature": 5.042871000000048, "downward_short_wave_radiation_flux": 22052864.0, "2_metre_temperature": 9.438135000000045, "dist": "20032.1688823", "temperature": 9.750940000000014, "minimum_temperature_at_2_metres": 8.781030000000044, "timestamp": "2021-02-15T00:00:00+00:00", "v_component_of_wind_gust": 4.717087, "total_water_precipitation": 2.476563, "relative_humidity": 74.039406, "u_component_of_wind_gust": 1.47438, "wind_speed_gust": 4.948173, "position": [47.5, 5.0], "forecast": "2021-02-17T15:00:00+00:00", "maximum_temperature_at_2_metres": 9.505334000000005, "total_cloud_cover": 69.0, "downward_long_wave_radiation_flux": 65452464.0}, "geometry": {"type": "Point", "coordinates": [5.0, 47.5]}, "record_timestamp": "2021-02-15T00:00:00+00:00"}, {"datasetid": "arpege-05-sp1_sp2", "recordid": "arpege_05_sp1_sp2_lastgrib20-2081141", "fields": {"2_metre_dewpoint_temperature": -3.4674440000000004, "downward_short_wave_radiation_flux": 0.0, "2_metre_temperature": -0.7848879999999667, "dist": "20032.1688823", "temperature": -1.1353519999999548, "minimum_temperature_at_2_metres": -0.9559079999999653, "timestamp": "2021-02-15T00:00:00+00:00", "v_component_of_wind_gust": 11.060577, "total_water_precipitation": 0.000977, "relative_humidity": 79.954781, "u_component_of_wind_gust": -2.611237, "wind_speed_gust": 11.362395, "position": [47.5, 5.0], "forecast": "2021-02-15T03:00:00+00:00", "maximum_temperature_at_2_metres": -0.761449999999968, "total_cloud_cover": 97.0, "downward_long_wave_radiation_flux": 2837922.0}, "geometry": {"type": "Point", "coordinates": [5.0, 47.5]}, "record_timestamp": "2021-02-15T00:00:00+00:00"}, {"datasetid": "arpege-05-sp1_sp2", "recordid": "arpege_05_sp1_sp2_lastgrib20-2081144", "fields": {"2_metre_dewpoint_temperature": -1.9410159999999905, "downward_short_wave_radiation_flux": 1704960.0, "2_metre_temperature": 2.135155999999995, "dist": "20032.1688823", "temperature": 2.3622380000000476, "minimum_temperature_at_2_metres": 0.4266300000000456, "timestamp": "2021-02-15T00:00:00+00:00", "v_component_of_wind_gust": 8.739426, "total_water_precipitation": 0.027344, "relative_humidity": 72.995071, "u_component_of_wind_gust": -1.42482, "wind_speed_gust": 8.873649, "position": [47.5, 5.0], "forecast": "2021-02-15T12:00:00+00:00", "maximum_temperature_at_2_metres": 2.1298160000000053, "total_cloud_cover": 94.5, "downward_long_wave_radiation_flux": 12094118.0}, "geometry": {"type": "Point", "coordinates": [5.0, 47.5]}, "record_timestamp": "2021-02-15T00:00:00+00:00"}, {"datasetid": "arpege-05-sp1_sp2", "recordid": "arpege_05_sp1_sp2_lastgrib20-2081149", "fields": {"2_metre_dewpoint_temperature": 1.4878170000000068, "downward_short_wave_radiation_flux": 3438592.0, "2_metre_temperature": 1.9207700000000045, "dist": "20032.1688823", "temperature": 1.3705080000000294, "minimum_temperature_at_2_metres": 1.9025510000000168, "timestamp": "2021-02-15T00:00:00+00:00", "v_component_of_wind_gust": 7.518951, "total_water_precipitation": 0.753906, "relative_humidity": 96.858986, "u_component_of_wind_gust": -1.235077, "wind_speed_gust": 7.624639, "position": [47.5, 5.0], "forecast": "2021-02-16T03:00:00+00:00", "maximum_temperature_at_2_metres": 2.063348000000019, "total_cloud_cover": 90.5, "downward_long_wave_radiation_flux": 28231544.0}, "geometry": {"type": "Point", "coordinates": [5.0, 47.5]}, "record_timestamp": "2021-02-15T00:00:00+00:00"}, {"datasetid": "arpege-05-sp1_sp2", "recordid": "arpege_05_sp1_sp2_lastgrib20-2081154", "fields": {"2_metre_dewpoint_temperature": 4.067957000000035, "downward_short_wave_radiation_flux": 12151808.0, "2_metre_temperature": 4.714135999999996, "dist": "20032.1688823", "temperature": 3.3632450000000063, "minimum_temperature_at_2_metres": 4.705774000000019, "timestamp": "2021-02-15T00:00:00+00:00", "v_component_of_wind_gust": 5.422043, "total_water_precipitation": 0.753906, "relative_humidity": 95.676025, "u_component_of_wind_gust": 1.227097, "wind_speed_gust": 5.562972, "position": [47.5, 5.0], "forecast": "2021-02-16T18:00:00+00:00", "maximum_temperature_at_2_metres": 8.008325000000013, "total_cloud_cover": 94.0, "downward_long_wave_radiation_flux": 43118688.0}, "geometry": {"type": "Point", "coordinates": [5.0, 47.5]}, "record_timestamp": "2021-02-15T00:00:00+00:00"}, {"datasetid": "arpege-05-sp1_sp2", "recordid": "arpege_05_sp1_sp2_lastgrib20-2081158", "fields": {"2_metre_dewpoint_temperature": 3.499261000000047, "downward_short_wave_radiation_flux": 12152832.0, "2_metre_temperature": 4.244348000000002, "dist": "20032.1688823", "temperature": 3.233728000000042, "minimum_temperature_at_2_metres": 4.230249000000015, "timestamp": "2021-02-15T00:00:00+00:00", "v_component_of_wind_gust": 1.482941, "total_water_precipitation": 2.476563, "relative_humidity": 94.988655, "u_component_of_wind_gust": 6.140991, "wind_speed_gust": 6.307765, "position": [47.5, 5.0], "forecast": "2021-02-17T06:00:00+00:00", "maximum_temperature_at_2_metres": 5.952112, "total_cloud_cover": 43.0, "downward_long_wave_radiation_flux": 57112480.0}, "geometry": {"type": "Point", "coordinates": [5.0, 47.5]}, "record_timestamp": "2021-02-15T00:00:00+00:00"}, {"datasetid": "arpege-05-sp1_sp2", "recordid": "arpege_05_sp1_sp2_lastgrib20-2081163", "fields": {"2_metre_dewpoint_temperature": 0.8169190000000413, "downward_short_wave_radiation_flux": 22753280.0, "2_metre_temperature": 0.9540039999999976, "dist": "20032.1688823", "temperature": -0.24576399999995147, "minimum_temperature_at_2_metres": 0.9627010000000382, "timestamp": "2021-02-15T00:00:00+00:00", "v_component_of_wind_gust": 0.86496, "total_water_precipitation": 2.476563, "relative_humidity": 98.860435, "u_component_of_wind_gust": 0.917999, "wind_speed_gust": 1.254705, "position": [47.5, 5.0], "forecast": "2021-02-17T21:00:00+00:00", "maximum_temperature_at_2_metres": 4.368982000000017, "total_cloud_cover": 64.0, "downward_long_wave_radiation_flux": 71056656.0}, "geometry": {"type": "Point", "coordinates": [5.0, 47.5]}, "record_timestamp": "2021-02-15T00:00:00+00:00"}, {"datasetid": "arpege-05-sp1_sp2", "recordid": "arpege_05_sp1_sp2_lastgrib20-2081159", "fields": {"2_metre_dewpoint_temperature": 4.361902000000043, "downward_short_wave_radiation_flux": 13152256.0, "2_metre_temperature": 4.87124, "dist": "20032.1688823", "temperature": 4.777612000000033, "minimum_temperature_at_2_metres": 3.2278080000000386, "timestamp": "2021-02-15T00:00:00+00:00", "v_component_of_wind_gust": 3.640015, "total_water_precipitation": 2.476563, "relative_humidity": 96.529015, "u_component_of_wind_gust": 3.524841, "wind_speed_gust": 5.069163, "position": [47.5, 5.0], "forecast": "2021-02-17T09:00:00+00:00", "maximum_temperature_at_2_metres": 4.866998000000024, "total_cloud_cover": 74.5, "downward_long_wave_radiation_flux": 59769136.0}, "geometry": {"type": "Point", "coordinates": [5.0, 47.5]}, "record_timestamp": "2021-02-15T00:00:00+00:00"}, {"datasetid": "arpege-05-sp1_sp2", "recordid": "arpege_05_sp1_sp2_lastgrib20-2081165", "fields": {"2_metre_dewpoint_temperature": 0.7854860000000485, "downward_short_wave_radiation_flux": 22753280.0, "2_metre_temperature": 0.7892700000000445, "dist": "20032.1688823", "temperature": 0.7625370000000089, "minimum_temperature_at_2_metres": 0.5361880000000383, "timestamp": "2021-02-15T00:00:00+00:00", "v_component_of_wind_gust": 1.808807, "total_water_precipitation": 2.484375, "relative_humidity": 99.999985, "u_component_of_wind_gust": -0.53389, "wind_speed_gust": 1.89173, "position": [47.5, 5.0], "forecast": "2021-02-18T03:00:00+00:00", "maximum_temperature_at_2_metres": 0.8382200000000353, "total_cloud_cover": 100.0, "downward_long_wave_radiation_flux": 77206144.0}, "geometry": {"type": "Point", "coordinates": [5.0, 47.5]}, "record_timestamp": "2021-02-15T00:00:00+00:00"}, {"datasetid": "arpege-05-sp1_sp2", "recordid": "arpege_05_sp1_sp2_lastgrib20-2081168", "fields": {"2_metre_dewpoint_temperature": 6.369470000000035, "downward_short_wave_radiation_flux": 25266176.0, "2_metre_temperature": 8.150720000000035, "dist": "20032.1688823", "temperature": 8.24276100000003, "timestamp": "2021-02-15T00:00:00+00:00", "v_component_of_wind_gust": 11.864624, "total_water_precipitation": 2.523438, "relative_humidity": 88.536911, "u_component_of_wind_gust": -1.006073, "wind_speed_gust": 11.917495, "position": [47.5, 5.0], "forecast": "2021-02-18T12:00:00+00:00", "downward_long_wave_radiation_flux": 87133408.0, "total_cloud_cover": 100.0}, "geometry": {"type": "Point", "coordinates": [5.0, 47.5]}, "record_timestamp": "2021-02-15T00:00:00+00:00"}, {"datasetid": "arpege-05-sp1_sp2", "recordid": "arpege_05_sp1_sp2_lastgrib20-2081173", "fields": {"2_metre_dewpoint_temperature": -0.5173399999999901, "downward_short_wave_radiation_flux": 27484160.0, "2_metre_temperature": 0.016076999999995678, "dist": "20032.1688823", "temperature": -1.011022999999966, "minimum_temperature_at_2_metres": 0.026941000000022086, "timestamp": "2021-02-15T00:00:00+00:00", "v_component_of_wind_gust": 1.803375, "total_water_precipitation": 4.984375, "relative_humidity": 95.581818, "u_component_of_wind_gust": 2.627335, "wind_speed_gust": 3.180218, "position": [47.5, 5.0], "forecast": "2021-02-19T06:00:00+00:00", "maximum_temperature_at_2_metres": 9.743738000000008, "total_cloud_cover": 100.0, "downward_long_wave_radiation_flux": 105160736.0}, "geometry": {"type": "Point", "coordinates": [5.0, 47.5]}, "record_timestamp": "2021-02-15T00:00:00+00:00"}, {"datasetid": "arpege-05-sp1_sp2", "recordid": "arpege_05_sp1_sp2_lastgrib20-2105642", "fields": {"2_metre_dewpoint_temperature": 5.353174000000024, "downward_short_wave_radiation_flux": 21735424.0, "2_metre_temperature": 5.656701999999996, "dist": "35947.108957", "temperature": 4.494989000000032, "minimum_temperature_at_2_metres": 5.659387000000038, "timestamp": "2021-02-15T00:00:00+00:00", "v_component_of_wind_gust": -0.917587, "total_water_precipitation": 2.039063, "relative_humidity": 97.797279, "u_component_of_wind_gust": 0.091949, "wind_speed_gust": 0.931002, "position": [47.0, 5.0], "forecast": "2021-02-17T18:00:00+00:00", "maximum_temperature_at_2_metres": 10.276392000000044, "total_cloud_cover": 67.0, "downward_long_wave_radiation_flux": 68825632.0}, "geometry": {"type": "Point", "coordinates": [5.0, 47.0]}, "record_timestamp": "2021-02-15T00:00:00+00:00"}, {"datasetid": "arpege-05-sp1_sp2", "recordid": "arpege_05_sp1_sp2_lastgrib20-2105649", "fields": {"2_metre_dewpoint_temperature": 7.884973000000002, "downward_short_wave_radiation_flux": 26867712.0, "2_metre_temperature": 10.846826000000021, "dist": "35947.108957", "temperature": 9.98266000000001, "minimum_temperature_at_2_metres": 2.0702760000000353, "timestamp": "2021-02-15T00:00:00+00:00", "v_component_of_wind_gust": 14.655594, "total_water_precipitation": 2.28125, "relative_humidity": 81.907509, "u_component_of_wind_gust": 1.286118, "wind_speed_gust": 14.721127, "position": [47.0, 5.0], "forecast": "2021-02-18T15:00:00+00:00", "maximum_temperature_at_2_metres": 11.966058000000032, "total_cloud_cover": 100.0, "downward_long_wave_radiation_flux": 91635488.0}, "geometry": {"type": "Point", "coordinates": [5.0, 47.0]}, "record_timestamp": "2021-02-15T00:00:00+00:00"}, {"datasetid": "arpege-05-sp1_sp2", "recordid": "arpege_05_sp1_sp2_lastgrib20-2105651", "fields": {"2_metre_dewpoint_temperature": 5.413416000000041, "downward_short_wave_radiation_flux": 26951680.0, "2_metre_temperature": 7.044519000000037, "dist": "35947.108957", "temperature": 6.13820800000002, "minimum_temperature_at_2_metres": 2.062097000000051, "timestamp": "2021-02-15T00:00:00+00:00", "v_component_of_wind_gust": 3.645691, "total_water_precipitation": 6.242188, "relative_humidity": 89.462692, "u_component_of_wind_gust": 5.630646, "wind_speed_gust": 6.713768, "position": [47.0, 5.0], "forecast": "2021-02-18T21:00:00+00:00", "maximum_temperature_at_2_metres": 11.95894800000002, "total_cloud_cover": 5.5, "downward_long_wave_radiation_flux": 98818640.0}, "geometry": {"type": "Point", "coordinates": [5.0, 47.0]}, "record_timestamp": "2021-02-15T00:00:00+00:00"}, {"datasetid": "arpege-05-sp1_sp2", "recordid": "arpege_05_sp1_sp2_lastgrib20-2105625", "fields": {"2_metre_dewpoint_temperature": 1.0645390000000248, "downward_short_wave_radiation_flux": 3975680.0, "2_metre_temperature": 5.242151000000035, "dist": "35947.108957", "temperature": 4.473352000000034, "minimum_temperature_at_2_metres": 4.5353640000000155, "timestamp": "2021-02-15T00:00:00+00:00", "v_component_of_wind_gust": 8.253021, "total_water_precipitation": 0.021484, "relative_humidity": 74.413933, "u_component_of_wind_gust": 2.631073, "wind_speed_gust": 8.660124, "position": [47.0, 5.0], "forecast": "2021-02-15T15:00:00+00:00", "maximum_temperature_at_2_metres": 5.4407900000000495, "total_cloud_cover": 95.0, "downward_long_wave_radiation_flux": 15292443.0}, "geometry": {"type": "Point", "coordinates": [5.0, 47.0]}, "record_timestamp": "2021-02-15T00:00:00+00:00"}, {"datasetid": "arpege-05-sp1_sp2", "recordid": "arpege_05_sp1_sp2_lastgrib20-2105630", "fields": {"2_metre_dewpoint_temperature": 2.550256000000047, "downward_short_wave_radiation_flux": 4092928.0, "2_metre_temperature": 3.499780000000044, "dist": "35947.108957", "temperature": 2.2574710000000096, "minimum_temperature_at_2_metres": 3.50356400000004, "timestamp": "2021-02-15T00:00:00+00:00", "v_component_of_wind_gust": 6.801224, "total_water_precipitation": 0.210938, "relative_humidity": 93.492928, "u_component_of_wind_gust": 2.125488, "wind_speed_gust": 7.139786, "position": [47.0, 5.0], "forecast": "2021-02-16T06:00:00+00:00", "maximum_temperature_at_2_metres": 3.7517330000000015, "total_cloud_cover": 99.5, "downward_long_wave_radiation_flux": 31254420.0}, "geometry": {"type": "Point", "coordinates": [5.0, 47.0]}, "record_timestamp": "2021-02-15T00:00:00+00:00"}, {"datasetid": "arpege-05-sp1_sp2", "recordid": "arpege_05_sp1_sp2_lastgrib20-2105632", "fields": {"2_metre_dewpoint_temperature": 6.519495000000006, "downward_short_wave_radiation_flux": 8030208.0, "2_metre_temperature": 9.190485000000024, "dist": "35947.108957", "temperature": 9.841821000000039, "minimum_temperature_at_2_metres": 5.047388000000012, "timestamp": "2021-02-15T00:00:00+00:00", "v_component_of_wind_gust": 8.94313, "total_water_precipitation": 0.210938, "relative_humidity": 83.479134, "u_component_of_wind_gust": 3.123062, "wind_speed_gust": 9.467167, "position": [47.0, 5.0], "forecast": "2021-02-16T12:00:00+00:00", "maximum_temperature_at_2_metres": 9.169152999999994, "total_cloud_cover": 96.5, "downward_long_wave_radiation_flux": 37856984.0}, "geometry": {"type": "Point", "coordinates": [5.0, 47.0]}, "record_timestamp": "2021-02-15T00:00:00+00:00"}, {"datasetid": "arpege-05-sp1_sp2", "recordid": "arpege_05_sp1_sp2_lastgrib20-2105633", "fields": {"2_metre_dewpoint_temperature": 7.460260000000005, "downward_short_wave_radiation_flux": 11607040.0, "2_metre_temperature": 10.417810000000031, "dist": "35947.108957", "temperature": 9.963098000000002, "minimum_temperature_at_2_metres": 9.399927000000048, "timestamp": "2021-02-15T00:00:00+00:00", "v_component_of_wind_gust": 10.186279, "total_water_precipitation": 0.207031, "relative_humidity": 81.974052, "u_component_of_wind_gust": 2.198715, "wind_speed_gust": 10.418905, "position": [47.0, 5.0], "forecast": "2021-02-16T15:00:00+00:00", "maximum_temperature_at_2_metres": 10.722986000000049, "total_cloud_cover": 100.0, "downward_long_wave_radiation_flux": 41046064.0}, "geometry": {"type": "Point", "coordinates": [5.0, 47.0]}, "record_timestamp": "2021-02-15T00:00:00+00:00"}, {"datasetid": "arpege-05-sp1_sp2", "recordid": "arpege_05_sp1_sp2_lastgrib20-2105637", "fields": {"2_metre_dewpoint_temperature": 3.7452030000000036, "downward_short_wave_radiation_flux": 12070912.0, "2_metre_temperature": 3.9413090000000466, "dist": "35947.108957", "temperature": 3.0838560000000257, "minimum_temperature_at_2_metres": 3.9354490000000055, "timestamp": "2021-02-15T00:00:00+00:00", "v_component_of_wind_gust": 4.831207, "total_water_precipitation": 2.039063, "relative_humidity": 98.727837, "u_component_of_wind_gust": 1.423065, "wind_speed_gust": 5.036902, "position": [47.0, 5.0], "forecast": "2021-02-17T03:00:00+00:00", "maximum_temperature_at_2_metres": 5.795831000000021, "total_cloud_cover": 44.5, "downward_long_wave_radiation_flux": 54086260.0}, "geometry": {"type": "Point", "coordinates": [5.0, 47.0]}, "record_timestamp": "2021-02-15T00:00:00+00:00"}, {"datasetid": "arpege-05-sp1_sp2", "recordid": "arpege_05_sp1_sp2_lastgrib20-2105638", "fields": {"2_metre_dewpoint_temperature": 2.311761000000047, "downward_short_wave_radiation_flux": 12070912.0, "2_metre_temperature": 2.4943480000000022, "dist": "35947.108957", "temperature": 1.483728000000042, "minimum_temperature_at_2_metres": 2.499780000000044, "timestamp": "2021-02-15T00:00:00+00:00", "v_component_of_wind_gust": 4.139191, "total_water_precipitation": 2.039063, "relative_humidity": 98.676155, "u_component_of_wind_gust": 1.640991, "wind_speed_gust": 4.464015, "position": [47.0, 5.0], "forecast": "2021-02-17T06:00:00+00:00", "maximum_temperature_at_2_metres": 3.5927369999999996, "total_cloud_cover": 67.0, "downward_long_wave_radiation_flux": 56940448.0}, "geometry": {"type": "Point", "coordinates": [5.0, 47.0]}, "record_timestamp": "2021-02-15T00:00:00+00:00"}, {"datasetid": "arpege-05-sp1_sp2", "recordid": "arpege_05_sp1_sp2_lastgrib20-2105623", "fields": {"2_metre_dewpoint_temperature": -3.488805999999954, "downward_short_wave_radiation_flux": 217600.0, "2_metre_temperature": 1.5226070000000504, "dist": "35947.108957", "temperature": 0.6613399999999956, "minimum_temperature_at_2_metres": 0.6212400000000002, "timestamp": "2021-02-15T00:00:00+00:00", "v_component_of_wind_gust": 8.141205, "total_water_precipitation": 0.0, "relative_humidity": 66.963913, "u_component_of_wind_gust": 3.109695, "wind_speed_gust": 8.716858, "position": [47.0, 5.0], "forecast": "2021-02-15T09:00:00+00:00", "maximum_temperature_at_2_metres": 1.5315800000000195, "total_cloud_cover": 99.5, "downward_long_wave_radiation_flux": 8789854.0}, "geometry": {"type": "Point", "coordinates": [5.0, 47.0]}, "record_timestamp": "2021-02-15T00:00:00+00:00"}, {"datasetid": "arpege-05-sp1_sp2", "recordid": "arpege_05_sp1_sp2_lastgrib20-2105634", "fields": {"2_metre_dewpoint_temperature": 6.130457000000035, "downward_short_wave_radiation_flux": 12069888.0, "2_metre_temperature": 7.339135999999996, "dist": "35947.108957", "temperature": 5.925745000000006, "minimum_temperature_at_2_metres": 7.3503050000000485, "timestamp": "2021-02-15T00:00:00+00:00", "v_component_of_wind_gust": 8.609543, "total_water_precipitation": 0.210938, "relative_humidity": 91.988525, "u_component_of_wind_gust": 2.789597, "wind_speed_gust": 9.047347, "position": [47.0, 5.0], "forecast": "2021-02-16T18:00:00+00:00", "maximum_temperature_at_2_metres": 10.135278000000028, "total_cloud_cover": 96.5, "downward_long_wave_radiation_flux": 44103776.0}, "geometry": {"type": "Point", "coordinates": [5.0, 47.0]}, "record_timestamp": "2021-02-15T00:00:00+00:00"}, {"datasetid": "arpege-05-sp1_sp2", "recordid": "arpege_05_sp1_sp2_lastgrib20-2105650", "fields": {"2_metre_dewpoint_temperature": 7.3866820000000075, "downward_short_wave_radiation_flux": 26953728.0, "2_metre_temperature": 9.176569000000029, "dist": "35947.108957", "temperature": 8.15249, "minimum_temperature_at_2_metres": 2.1070799999999963, "timestamp": "2021-02-15T00:00:00+00:00", "v_component_of_wind_gust": 6.673523, "total_water_precipitation": 6.210938, "relative_humidity": 88.551331, "u_component_of_wind_gust": 7.445847, "wind_speed_gust": 10.007014, "position": [47.0, 5.0], "forecast": "2021-02-18T18:00:00+00:00", "maximum_temperature_at_2_metres": 12.003625, "total_cloud_cover": 100.0, "downward_long_wave_radiation_flux": 95316704.0}, "geometry": {"type": "Point", "coordinates": [5.0, 47.0]}, "record_timestamp": "2021-02-15T00:00:00+00:00"}, {"datasetid": "arpege-05-sp1_sp2", "recordid": "arpege_05_sp1_sp2_lastgrib20-2105621", "fields": {"2_metre_dewpoint_temperature": -3.3424440000000004, "downward_short_wave_radiation_flux": 0.0, "2_metre_temperature": 0.8088620000000333, "dist": "35947.108957", "temperature": -0.5103519999999548, "minimum_temperature_at_2_metres": 0.5694820000000504, "timestamp": "2021-02-15T00:00:00+00:00", "v_component_of_wind_gust": 8.904327, "total_water_precipitation": 0.0, "relative_humidity": 71.486031, "u_component_of_wind_gust": 1.857513, "wind_speed_gust": 9.09677, "position": [47.0, 5.0], "forecast": "2021-02-15T03:00:00+00:00", "maximum_temperature_at_2_metres": 0.8088620000000333, "total_cloud_cover": 95.0, "downward_long_wave_radiation_flux": 2838498.0}, "geometry": {"type": "Point", "coordinates": [5.0, 47.0]}, "record_timestamp": "2021-02-15T00:00:00+00:00"}, {"datasetid": "arpege-05-sp1_sp2", "recordid": "arpege_05_sp1_sp2_lastgrib20-2105648", "fields": {"2_metre_dewpoint_temperature": 7.838220000000035, "downward_short_wave_radiation_flux": 24696832.0, "2_metre_temperature": 11.119470000000035, "dist": "35947.108957", "temperature": 10.99276100000003, "timestamp": "2021-02-15T00:00:00+00:00", "v_component_of_wind_gust": 12.677124, "total_water_precipitation": 2.109375, "relative_humidity": 80.193161, "u_component_of_wind_gust": 3.212677, "wind_speed_gust": 13.073745, "position": [47.0, 5.0], "forecast": "2021-02-18T12:00:00+00:00", "downward_long_wave_radiation_flux": 88147168.0, "total_cloud_cover": 100.0}, "geometry": {"type": "Point", "coordinates": [5.0, 47.0]}, "record_timestamp": "2021-02-15T00:00:00+00:00"}, {"datasetid": "arpege-05-sp1_sp2", "recordid": "arpege_05_sp1_sp2_lastgrib20-2105622", "fields": {"2_metre_dewpoint_temperature": -3.7973389999999654, "downward_short_wave_radiation_flux": 0.0, "2_metre_temperature": 0.6212100000000191, "dist": "35947.108957", "temperature": -0.6044069999999806, "minimum_temperature_at_2_metres": 0.6056150000000002, "timestamp": "2021-02-15T00:00:00+00:00", "v_component_of_wind_gust": 7.911652, "total_water_precipitation": 0.0, "relative_humidity": 69.800514, "u_component_of_wind_gust": 2.862473, "wind_speed_gust": 8.400084, "position": [47.0, 5.0], "forecast": "2021-02-15T06:00:00+00:00", "maximum_temperature_at_2_metres": 0.9669130000000337, "total_cloud_cover": 100.0, "downward_long_wave_radiation_flux": 5738057.0}, "geometry": {"type": "Point", "coordinates": [5.0, 47.0]}, "record_timestamp": "2021-02-15T00:00:00+00:00"}, {"datasetid": "arpege-05-sp1_sp2", "recordid": "arpege_05_sp1_sp2_lastgrib20-2105627", "fields": {"2_metre_dewpoint_temperature": 1.0767460000000142, "downward_short_wave_radiation_flux": 4092928.0, "2_metre_temperature": 3.012354000000016, "dist": "35947.108957", "temperature": 1.696313000000032, "minimum_temperature_at_2_metres": 3.0268800000000056, "timestamp": "2021-02-15T00:00:00+00:00", "v_component_of_wind_gust": 8.057175, "total_water_precipitation": 0.205078, "relative_humidity": 87.004265, "u_component_of_wind_gust": 2.549942, "wind_speed_gust": 8.446545, "position": [47.0, 5.0], "forecast": "2021-02-15T21:00:00+00:00", "maximum_temperature_at_2_metres": 3.553674000000001, "total_cloud_cover": 94.5, "downward_long_wave_radiation_flux": 21664520.0}, "geometry": {"type": "Point", "coordinates": [5.0, 47.0]}, "record_timestamp": "2021-02-15T00:00:00+00:00"}, {"datasetid": "arpege-05-sp1_sp2", "recordid": "arpege_05_sp1_sp2_lastgrib20-2105643", "fields": {"2_metre_dewpoint_temperature": 1.8169190000000413, "downward_short_wave_radiation_flux": 21733376.0, "2_metre_temperature": 1.8602539999999976, "dist": "35947.108957", "temperature": 1.0667360000000485, "minimum_temperature_at_2_metres": 1.876764000000037, "timestamp": "2021-02-15T00:00:00+00:00", "v_component_of_wind_gust": -0.869415, "total_water_precipitation": 2.039063, "relative_humidity": 99.672935, "u_component_of_wind_gust": -0.082001, "wind_speed_gust": 0.86408, "position": [47.0, 5.0], "forecast": "2021-02-17T21:00:00+00:00", "maximum_temperature_at_2_metres": 5.361169000000018, "total_cloud_cover": 62.0, "downward_long_wave_radiation_flux": 71642384.0}, "geometry": {"type": "Point", "coordinates": [5.0, 47.0]}, "record_timestamp": "2021-02-15T00:00:00+00:00"}, {"datasetid": "arpege-05-sp1_sp2", "recordid": "arpege_05_sp1_sp2_lastgrib20-2105644", "fields": {"2_metre_dewpoint_temperature": 0.5385380000000168, "downward_short_wave_radiation_flux": 21735424.0, "2_metre_temperature": 0.5507450000000063, "dist": "35947.108957", "temperature": 0.5179690000000505, "minimum_temperature_at_2_metres": 0.5253850000000284, "timestamp": "2021-02-15T00:00:00+00:00", "v_component_of_wind_gust": -0.489685, "total_water_precipitation": 2.046875, "relative_humidity": 99.960823, "u_component_of_wind_gust": 0.165939, "wind_speed_gust": 0.523299, "position": [47.0, 5.0], "forecast": "2021-02-18T00:00:00+00:00", "maximum_temperature_at_2_metres": 1.67562300000003, "total_cloud_cover": 100.0, "downward_long_wave_radiation_flux": 74626736.0}, "geometry": {"type": "Point", "coordinates": [5.0, 47.0]}, "record_timestamp": "2021-02-15T00:00:00+00:00"}, {"datasetid": "arpege-05-sp1_sp2", "recordid": "arpege_05_sp1_sp2_lastgrib20-2105645", "fields": {"2_metre_dewpoint_temperature": 1.0042360000000485, "downward_short_wave_radiation_flux": 21735424.0, "2_metre_temperature": 1.0392700000000445, "dist": "35947.108957", "temperature": 1.356287000000009, "minimum_temperature_at_2_metres": 0.7842350000000238, "timestamp": "2021-02-15T00:00:00+00:00", "v_component_of_wind_gust": -1.409943, "total_water_precipitation": 2.054688, "relative_humidity": 99.656235, "u_component_of_wind_gust": -2.34639, "wind_speed_gust": 2.719855, "position": [47.0, 5.0], "forecast": "2021-02-18T03:00:00+00:00", "maximum_temperature_at_2_metres": 1.2073610000000485, "total_cloud_cover": 100.0, "downward_long_wave_radiation_flux": 78043776.0}, "geometry": {"type": "Point", "coordinates": [5.0, 47.0]}, "record_timestamp": "2021-02-15T00:00:00+00:00"}, {"datasetid": "arpege-05-sp1_sp2", "recordid": "arpege_05_sp1_sp2_lastgrib20-2105647", "fields": {"2_metre_dewpoint_temperature": 5.575800000000015, "downward_short_wave_radiation_flux": 22370304.0, "2_metre_temperature": 6.905327999999997, "dist": "35947.108957", "temperature": 6.243188000000032, "minimum_temperature_at_2_metres": 1.7764530000000036, "timestamp": "2021-02-15T00:00:00+00:00", "v_component_of_wind_gust": 8.548523, "total_water_precipitation": 2.070313, "relative_humidity": 91.276291, "u_component_of_wind_gust": 3.972656, "wind_speed_gust": 9.427629, "position": [47.0, 5.0], "forecast": "2021-02-18T09:00:00+00:00", "maximum_temperature_at_2_metres": 6.901971000000003, "total_cloud_cover": 99.0, "downward_long_wave_radiation_flux": 84788000.0}, "geometry": {"type": "Point", "coordinates": [5.0, 47.0]}, "record_timestamp": "2021-02-15T00:00:00+00:00"}, {"datasetid": "arpege-05-sp1_sp2", "recordid": "arpege_05_sp1_sp2_lastgrib20-2105635", "fields": {"2_metre_dewpoint_temperature": 5.61641800000001, "downward_short_wave_radiation_flux": 12069888.0, "2_metre_temperature": 6.215814000000023, "dist": "35947.108957", "temperature": 5.359491000000048, "minimum_temperature_at_2_metres": 6.204094999999995, "timestamp": "2021-02-15T00:00:00+00:00", "v_component_of_wind_gust": 7.034439, "total_water_precipitation": 0.558594, "relative_humidity": 95.974167, "u_component_of_wind_gust": 2.238052, "wind_speed_gust": 7.385554, "position": [47.0, 5.0], "forecast": "2021-02-16T21:00:00+00:00", "maximum_temperature_at_2_metres": 7.339624000000015, "total_cloud_cover": 95.0, "downward_long_wave_radiation_flux": 47419936.0}, "geometry": {"type": "Point", "coordinates": [5.0, 47.0]}, "record_timestamp": "2021-02-15T00:00:00+00:00"}, {"datasetid": "arpege-05-sp1_sp2", "recordid": "arpege_05_sp1_sp2_lastgrib20-2105639", "fields": {"2_metre_dewpoint_temperature": 4.768152000000043, "downward_short_wave_radiation_flux": 13064192.0, "2_metre_temperature": 5.08999, "dist": "35947.108957", "temperature": 5.058862000000033, "minimum_temperature_at_2_metres": 2.5188229999999976, "timestamp": "2021-02-15T00:00:00+00:00", "v_component_of_wind_gust": 4.515015, "total_water_precipitation": 2.039063, "relative_humidity": 97.779015, "u_component_of_wind_gust": 0.087341, "wind_speed_gust": 4.522288, "position": [47.0, 5.0], "forecast": "2021-02-17T09:00:00+00:00", "maximum_temperature_at_2_metres": 5.083795000000009, "total_cloud_cover": 70.5, "downward_long_wave_radiation_flux": 59744560.0}, "geometry": {"type": "Point", "coordinates": [5.0, 47.0]}, "record_timestamp": "2021-02-15T00:00:00+00:00"}, {"datasetid": "arpege-05-sp1_sp2", "recordid": "arpege_05_sp1_sp2_lastgrib20-2105620", "fields": {"2_metre_dewpoint_temperature": -2.8139400000000023, "2_metre_temperature": 0.7945799999999963, "dist": "35947.108957", "temperature": -0.14737499999995407, "timestamp": "2021-02-15T00:00:00+00:00", "forecast": "2021-02-15T00:00:00+00:00", "relative_humidity": 74.729233, "position": [47.0, 5.0], "total_cloud_cover": 100.0}, "geometry": {"type": "Point", "coordinates": [5.0, 47.0]}, "record_timestamp": "2021-02-15T00:00:00+00:00"}, {"datasetid": "arpege-05-sp1_sp2", "recordid": "arpege_05_sp1_sp2_lastgrib20-2105646", "fields": {"2_metre_dewpoint_temperature": 2.0780880000000366, "downward_short_wave_radiation_flux": 21735424.0, "2_metre_temperature": 2.111261000000013, "dist": "35947.108957", "temperature": 2.084924000000001, "minimum_temperature_at_2_metres": 1.160425000000032, "timestamp": "2021-02-15T00:00:00+00:00", "v_component_of_wind_gust": -1.147461, "total_water_precipitation": 2.070313, "relative_humidity": 99.793137, "u_component_of_wind_gust": 0.092239, "wind_speed_gust": 1.15858, "position": [47.0, 5.0], "forecast": "2021-02-18T06:00:00+00:00", "maximum_temperature_at_2_metres": 2.112390000000005, "total_cloud_cover": 99.0, "downward_long_wave_radiation_flux": 81525008.0}, "geometry": {"type": "Point", "coordinates": [5.0, 47.0]}, "record_timestamp": "2021-02-15T00:00:00+00:00"}, {"datasetid": "arpege-05-sp1_sp2", "recordid": "arpege_05_sp1_sp2_lastgrib20-2105652", "fields": {"2_metre_dewpoint_temperature": 3.0141849999999977, "downward_short_wave_radiation_flux": 26951680.0, "2_metre_temperature": 3.5089360000000056, "dist": "35947.108957", "temperature": 2.44356700000003, "minimum_temperature_at_2_metres": 1.7431270000000154, "timestamp": "2021-02-15T00:00:00+00:00", "v_component_of_wind_gust": 3.287491, "total_water_precipitation": 6.25, "relative_humidity": 96.590111, "u_component_of_wind_gust": 1.054214, "wind_speed_gust": 3.461404, "position": [47.0, 5.0], "forecast": "2021-02-19T00:00:00+00:00", "maximum_temperature_at_2_metres": 11.639673000000016, "total_cloud_cover": 97.5, "downward_long_wave_radiation_flux": 101591600.0}, "geometry": {"type": "Point", "coordinates": [5.0, 47.0]}, "record_timestamp": "2021-02-15T00:00:00+00:00"}, {"datasetid": "arpege-05-sp1_sp2", "recordid": "arpege_05_sp1_sp2_lastgrib20-2105653", "fields": {"2_metre_dewpoint_temperature": 0.13891000000000986, "downward_short_wave_radiation_flux": 26951680.0, "2_metre_temperature": 0.20357699999999568, "dist": "35947.108957", "temperature": -0.26102299999996603, "minimum_temperature_at_2_metres": 0.21248800000000756, "timestamp": "2021-02-15T00:00:00+00:00", "v_component_of_wind_gust": 1.194, "total_water_precipitation": 6.25, "relative_humidity": 99.456818, "u_component_of_wind_gust": 1.67421, "wind_speed_gust": 2.055218, "position": [47.0, 5.0], "forecast": "2021-02-19T06:00:00+00:00", "maximum_temperature_at_2_metres": 11.591394000000037, "total_cloud_cover": 100.0, "downward_long_wave_radiation_flux": 107061280.0}, "geometry": {"type": "Point", "coordinates": [5.0, 47.0]}, "record_timestamp": "2021-02-15T00:00:00+00:00"}, {"datasetid": "arpege-05-sp1_sp2", "recordid": "arpege_05_sp1_sp2_lastgrib20-2105624", "fields": {"2_metre_dewpoint_temperature": -0.9722659999999905, "downward_short_wave_radiation_flux": 1978368.0, "2_metre_temperature": 4.416405999999995, "dist": "35947.108957", "temperature": 4.174738000000048, "minimum_temperature_at_2_metres": 1.6942080000000033, "timestamp": "2021-02-15T00:00:00+00:00", "v_component_of_wind_gust": 10.458176, "total_water_precipitation": 0.005859, "relative_humidity": 67.245071, "u_component_of_wind_gust": 2.88768, "wind_speed_gust": 10.858024, "position": [47.0, 5.0], "forecast": "2021-02-15T12:00:00+00:00", "maximum_temperature_at_2_metres": 4.426691000000005, "total_cloud_cover": 99.5, "downward_long_wave_radiation_flux": 12035494.0}, "geometry": {"type": "Point", "coordinates": [5.0, 47.0]}, "record_timestamp": "2021-02-15T00:00:00+00:00"}, {"datasetid": "arpege-05-sp1_sp2", "recordid": "arpege_05_sp1_sp2_lastgrib20-2105626", "fields": {"2_metre_dewpoint_temperature": 1.2050420000000486, "downward_short_wave_radiation_flux": 4092928.0, "2_metre_temperature": 3.6745240000000194, "dist": "35947.108957", "temperature": 2.2326290000000313, "minimum_temperature_at_2_metres": 3.664758000000006, "timestamp": "2021-02-15T00:00:00+00:00", "v_component_of_wind_gust": 7.864655, "total_water_precipitation": 0.205078, "relative_humidity": 83.85524, "u_component_of_wind_gust": 2.548172, "wind_speed_gust": 8.25139, "position": [47.0, 5.0], "forecast": "2021-02-15T18:00:00+00:00", "maximum_temperature_at_2_metres": 5.115259000000037, "total_cloud_cover": 100.0, "downward_long_wave_radiation_flux": 18608576.0}, "geometry": {"type": "Point", "coordinates": [5.0, 47.0]}, "record_timestamp": "2021-02-15T00:00:00+00:00"}, {"datasetid": "arpege-05-sp1_sp2", "recordid": "arpege_05_sp1_sp2_lastgrib20-2105628", "fields": {"2_metre_dewpoint_temperature": 2.0413450000000353, "downward_short_wave_radiation_flux": 4092928.0, "2_metre_temperature": 3.2957700000000045, "dist": "35947.108957", "temperature": 2.2177670000000376, "minimum_temperature_at_2_metres": 2.8797550000000456, "timestamp": "2021-02-15T00:00:00+00:00", "v_component_of_wind_gust": 7.651001, "total_water_precipitation": 0.208984, "relative_humidity": 91.392151, "u_component_of_wind_gust": 3.597351, "wind_speed_gust": 8.446295, "position": [47.0, 5.0], "forecast": "2021-02-16T00:00:00+00:00", "maximum_temperature_at_2_metres": 3.2830749999999966, "total_cloud_cover": 97.0, "downward_long_wave_radiation_flux": 24794760.0}, "geometry": {"type": "Point", "coordinates": [5.0, 47.0]}, "record_timestamp": "2021-02-15T00:00:00+00:00"}, {"datasetid": "arpege-05-sp1_sp2", "recordid": "arpege_05_sp1_sp2_lastgrib20-2105629", "fields": {"2_metre_dewpoint_temperature": 2.706567000000007, "downward_short_wave_radiation_flux": 4092928.0, "2_metre_temperature": 3.7332700000000045, "dist": "35947.108957", "temperature": 2.6830080000000294, "minimum_temperature_at_2_metres": 3.3107540000000313, "timestamp": "2021-02-15T00:00:00+00:00", "v_component_of_wind_gust": 7.081451, "total_water_precipitation": 0.208984, "relative_humidity": 93.077736, "u_component_of_wind_gust": 3.046173, "wind_speed_gust": 7.702764, "position": [47.0, 5.0], "forecast": "2021-02-16T03:00:00+00:00", "maximum_temperature_at_2_metres": 3.799677000000031, "total_cloud_cover": 97.0, "downward_long_wave_radiation_flux": 28106616.0}, "geometry": {"type": "Point", "coordinates": [5.0, 47.0]}, "record_timestamp": "2021-02-15T00:00:00+00:00"}, {"datasetid": "arpege-05-sp1_sp2", "recordid": "arpege_05_sp1_sp2_lastgrib20-2105631", "fields": {"2_metre_dewpoint_temperature": 3.5939580000000433, "downward_short_wave_radiation_flux": 4727808.0, "2_metre_temperature": 4.937280000000044, "dist": "35947.108957", "temperature": 4.627924000000007, "minimum_temperature_at_2_metres": 3.477106000000049, "timestamp": "2021-02-15T00:00:00+00:00", "v_component_of_wind_gust": 8.056793, "total_water_precipitation": 0.210938, "relative_humidity": 90.921043, "u_component_of_wind_gust": 2.945862, "wind_speed_gust": 8.579565, "position": [47.0, 5.0], "forecast": "2021-02-16T09:00:00+00:00", "maximum_temperature_at_2_metres": 4.953576999999996, "total_cloud_cover": 90.5, "downward_long_wave_radiation_flux": 34388812.0}, "geometry": {"type": "Point", "coordinates": [5.0, 47.0]}, "record_timestamp": "2021-02-15T00:00:00+00:00"}, {"datasetid": "arpege-05-sp1_sp2", "recordid": "arpege_05_sp1_sp2_lastgrib20-2105636", "fields": {"2_metre_dewpoint_temperature": 5.591516000000013, "downward_short_wave_radiation_flux": 12070912.0, "2_metre_temperature": 6.034020999999996, "dist": "35947.108957", "temperature": 5.460565000000031, "minimum_temperature_at_2_metres": 5.963707999999997, "timestamp": "2021-02-15T00:00:00+00:00", "v_component_of_wind_gust": 7.337753, "total_water_precipitation": 2.039063, "relative_humidity": 97.072525, "u_component_of_wind_gust": 1.249634, "wind_speed_gust": 7.440844, "position": [47.0, 5.0], "forecast": "2021-02-17T00:00:00+00:00", "maximum_temperature_at_2_metres": 6.216089000000011, "total_cloud_cover": 50.0, "downward_long_wave_radiation_flux": 51007688.0}, "geometry": {"type": "Point", "coordinates": [5.0, 47.0]}, "record_timestamp": "2021-02-15T00:00:00+00:00"}, {"datasetid": "arpege-05-sp1_sp2", "recordid": "arpege_05_sp1_sp2_lastgrib20-2105640", "fields": {"2_metre_dewpoint_temperature": 6.968042000000025, "downward_short_wave_radiation_flux": 16506880.0, "2_metre_temperature": 8.674097000000017, "dist": "35947.108957", "temperature": 10.630121000000031, "minimum_temperature_at_2_metres": 5.486626999999999, "timestamp": "2021-02-15T00:00:00+00:00", "v_component_of_wind_gust": 4.043747, "total_water_precipitation": 2.039063, "relative_humidity": 89.000267, "u_component_of_wind_gust": 3.991013, "wind_speed_gust": 5.68474, "position": [47.0, 5.0], "forecast": "2021-02-17T12:00:00+00:00", "maximum_temperature_at_2_metres": 8.676691000000005, "total_cloud_cover": 57.5, "downward_long_wave_radiation_flux": 63085056.0}, "geometry": {"type": "Point", "coordinates": [5.0, 47.0]}, "record_timestamp": "2021-02-15T00:00:00+00:00"}, {"datasetid": "arpege-05-sp1_sp2", "recordid": "arpege_05_sp1_sp2_lastgrib20-2105641", "fields": {"2_metre_dewpoint_temperature": 7.605371000000048, "downward_short_wave_radiation_flux": 20920320.0, "2_metre_temperature": 10.250635000000045, "dist": "35947.108957", "temperature": 11.157190000000014, "minimum_temperature_at_2_metres": 8.894312000000014, "timestamp": "2021-02-15T00:00:00+00:00", "v_component_of_wind_gust": 3.482712, "total_water_precipitation": 2.039063, "relative_humidity": 83.664406, "u_component_of_wind_gust": 3.41188, "wind_speed_gust": 4.870048, "position": [47.0, 5.0], "forecast": "2021-02-17T15:00:00+00:00", "maximum_temperature_at_2_metres": 10.231897000000004, "total_cloud_cover": 56.0, "downward_long_wave_radiation_flux": 66005424.0}, "geometry": {"type": "Point", "coordinates": [5.0, 47.0]}, "record_timestamp": "2021-02-15T00:00:00+00:00"}, {"datasetid": "arpege-05-sp1_sp2", "recordid": "arpege_05_sp1_sp2_lastgrib20-2081194", "fields": {"2_metre_dewpoint_temperature": 6.499292000000025, "downward_short_wave_radiation_flux": 14901248.0, "2_metre_temperature": 7.1740970000000175, "dist": "39774.6444262", "temperature": 9.005121000000031, "minimum_temperature_at_2_metres": 4.873346000000026, "timestamp": "2021-02-15T00:00:00+00:00", "v_component_of_wind_gust": 3.293747, "total_water_precipitation": 4.644531, "relative_humidity": 95.437767, "u_component_of_wind_gust": 4.053513, "wind_speed_gust": 5.21599, "position": [47.5, 5.5], "forecast": "2021-02-17T12:00:00+00:00", "maximum_temperature_at_2_metres": 7.1845030000000065, "total_cloud_cover": 88.5, "downward_long_wave_radiation_flux": 64973312.0}, "geometry": {"type": "Point", "coordinates": [5.5, 47.5]}, "record_timestamp": "2021-02-15T00:00:00+00:00"}, {"datasetid": "arpege-05-sp1_sp2", "recordid": "arpege_05_sp1_sp2_lastgrib20-2081203", "fields": {"2_metre_dewpoint_temperature": 7.728723000000002, "downward_short_wave_radiation_flux": 24846336.0, "2_metre_temperature": 10.690576000000021, "dist": "39774.6444262", "temperature": 9.73266000000001, "minimum_temperature_at_2_metres": -0.8066769999999792, "timestamp": "2021-02-15T00:00:00+00:00", "v_component_of_wind_gust": 14.218094, "total_water_precipitation": 4.75, "relative_humidity": 82.032509, "u_component_of_wind_gust": 6.598618, "wind_speed_gust": 15.689877, "position": [47.5, 5.5], "forecast": "2021-02-18T15:00:00+00:00", "maximum_temperature_at_2_metres": 11.321527000000003, "total_cloud_cover": 99.0, "downward_long_wave_radiation_flux": 92487456.0}, "geometry": {"type": "Point", "coordinates": [5.5, 47.5]}, "record_timestamp": "2021-02-15T00:00:00+00:00"}, {"datasetid": "arpege-05-sp1_sp2", "recordid": "arpege_05_sp1_sp2_lastgrib20-2081175", "fields": {"2_metre_dewpoint_temperature": -3.8111940000000004, "downward_short_wave_radiation_flux": 0.0, "2_metre_temperature": -0.2536379999999667, "dist": "39774.6444262", "temperature": -1.6041019999999548, "minimum_temperature_at_2_metres": -1.0945799999999508, "timestamp": "2021-02-15T00:00:00+00:00", "v_component_of_wind_gust": 6.873077, "total_water_precipitation": 0.0, "relative_humidity": 74.392281, "u_component_of_wind_gust": -0.454987, "wind_speed_gust": 6.893646, "position": [47.5, 5.5], "forecast": "2021-02-15T03:00:00+00:00", "maximum_temperature_at_2_metres": -0.277074999999968, "total_cloud_cover": 96.0, "downward_long_wave_radiation_flux": 2893474.0}, "geometry": {"type": "Point", "coordinates": [5.5, 47.5]}, "record_timestamp": "2021-02-15T00:00:00+00:00"}, {"datasetid": "arpege-05-sp1_sp2", "recordid": "arpege_05_sp1_sp2_lastgrib20-2081180", "fields": {"2_metre_dewpoint_temperature": 1.4550420000000486, "downward_short_wave_radiation_flux": 3508224.0, "2_metre_temperature": 3.0807740000000194, "dist": "39774.6444262", "temperature": 2.0451290000000313, "minimum_temperature_at_2_metres": 3.063196000000005, "timestamp": "2021-02-15T00:00:00+00:00", "v_component_of_wind_gust": 8.052155, "total_water_precipitation": 0.46875, "relative_humidity": 89.23024, "u_component_of_wind_gust": 3.704422, "wind_speed_gust": 8.860765, "position": [47.5, 5.5], "forecast": "2021-02-15T18:00:00+00:00", "maximum_temperature_at_2_metres": 4.078148999999996, "total_cloud_cover": 93.0, "downward_long_wave_radiation_flux": 18772416.0}, "geometry": {"type": "Point", "coordinates": [5.5, 47.5]}, "record_timestamp": "2021-02-15T00:00:00+00:00"}, {"datasetid": "arpege-05-sp1_sp2", "recordid": "arpege_05_sp1_sp2_lastgrib20-2081193", "fields": {"2_metre_dewpoint_temperature": 4.674402000000043, "downward_short_wave_radiation_flux": 12365824.0, "2_metre_temperature": 4.74624, "dist": "39774.6444262", "temperature": 5.121362000000033, "minimum_temperature_at_2_metres": 3.5422609999999963, "timestamp": "2021-02-15T00:00:00+00:00", "v_component_of_wind_gust": 5.233765, "total_water_precipitation": 4.640625, "relative_humidity": 99.341515, "u_component_of_wind_gust": 1.524841, "wind_speed_gust": 5.444163, "position": [47.5, 5.5], "forecast": "2021-02-17T09:00:00+00:00", "maximum_temperature_at_2_metres": 4.757623000000024, "total_cloud_cover": 97.5, "downward_long_wave_radiation_flux": 61323568.0}, "geometry": {"type": "Point", "coordinates": [5.5, 47.5]}, "record_timestamp": "2021-02-15T00:00:00+00:00"}, {"datasetid": "arpege-05-sp1_sp2", "recordid": "arpege_05_sp1_sp2_lastgrib20-2081196", "fields": {"2_metre_dewpoint_temperature": 4.478174000000024, "downward_short_wave_radiation_flux": 19509248.0, "2_metre_temperature": 5.250451999999996, "dist": "39774.6444262", "temperature": 3.7449890000000323, "minimum_temperature_at_2_metres": 5.233606000000009, "timestamp": "2021-02-15T00:00:00+00:00", "v_component_of_wind_gust": 2.301163, "total_water_precipitation": 4.644531, "relative_humidity": 94.922279, "u_component_of_wind_gust": 0.685699, "wind_speed_gust": 2.399752, "position": [47.5, 5.5], "forecast": "2021-02-17T18:00:00+00:00", "maximum_temperature_at_2_metres": 9.961938000000032, "total_cloud_cover": 100.0, "downward_long_wave_radiation_flux": 70894112.0}, "geometry": {"type": "Point", "coordinates": [5.5, 47.5]}, "record_timestamp": "2021-02-15T00:00:00+00:00"}, {"datasetid": "arpege-05-sp1_sp2", "recordid": "arpege_05_sp1_sp2_lastgrib20-2081197", "fields": {"2_metre_dewpoint_temperature": 1.5981690000000413, "downward_short_wave_radiation_flux": 19507200.0, "2_metre_temperature": 1.6727539999999976, "dist": "39774.6444262", "temperature": 0.5042360000000485, "minimum_temperature_at_2_metres": 1.6834050000000502, "timestamp": "2021-02-15T00:00:00+00:00", "v_component_of_wind_gust": -1.07254, "total_water_precipitation": 4.648438, "relative_humidity": 99.297935, "u_component_of_wind_gust": -0.332001, "wind_speed_gust": 1.129705, "position": [47.5, 5.5], "forecast": "2021-02-17T21:00:00+00:00", "maximum_temperature_at_2_metres": 5.1092160000000035, "total_cloud_cover": 78.0, "downward_long_wave_radiation_flux": 73645328.0}, "geometry": {"type": "Point", "coordinates": [5.5, 47.5]}, "record_timestamp": "2021-02-15T00:00:00+00:00"}, {"datasetid": "arpege-05-sp1_sp2", "recordid": "arpege_05_sp1_sp2_lastgrib20-2081206", "fields": {"2_metre_dewpoint_temperature": 2.3266849999999977, "downward_short_wave_radiation_flux": 24969216.0, "2_metre_temperature": 3.0714360000000056, "dist": "39774.6444262", "temperature": 1.81856700000003, "minimum_temperature_at_2_metres": -0.8955439999999726, "timestamp": "2021-02-15T00:00:00+00:00", "v_component_of_wind_gust": 1.365616, "total_water_precipitation": 9.734375, "relative_humidity": 94.840111, "u_component_of_wind_gust": 3.054214, "wind_speed_gust": 3.352029, "position": [47.5, 5.5], "forecast": "2021-02-19T00:00:00+00:00", "maximum_temperature_at_2_metres": 11.23537600000003, "total_cloud_cover": 64.0, "downward_long_wave_radiation_flux": 102482480.0}, "geometry": {"type": "Point", "coordinates": [5.5, 47.5]}, "record_timestamp": "2021-02-15T00:00:00+00:00"}, {"datasetid": "arpege-05-sp1_sp2", "recordid": "arpege_05_sp1_sp2_lastgrib20-2081178", "fields": {"2_metre_dewpoint_temperature": -1.0660159999999905, "downward_short_wave_radiation_flux": 2120192.0, "2_metre_temperature": 3.635155999999995, "dist": "39774.6444262", "temperature": 3.5184880000000476, "minimum_temperature_at_2_metres": 1.3113950000000045, "timestamp": "2021-02-15T00:00:00+00:00", "v_component_of_wind_gust": 10.645676, "total_water_precipitation": 0.025391, "relative_humidity": 70.588821, "u_component_of_wind_gust": 4.01268, "wind_speed_gust": 11.373649, "position": [47.5, 5.5], "forecast": "2021-02-15T12:00:00+00:00", "maximum_temperature_at_2_metres": 3.620050000000049, "total_cloud_cover": 99.5, "downward_long_wave_radiation_flux": 12113318.0}, "geometry": {"type": "Point", "coordinates": [5.5, 47.5]}, "record_timestamp": "2021-02-15T00:00:00+00:00"}, {"datasetid": "arpege-05-sp1_sp2", "recordid": "arpege_05_sp1_sp2_lastgrib20-2081179", "fields": {"2_metre_dewpoint_temperature": 0.7207890000000248, "downward_short_wave_radiation_flux": 3422208.0, "2_metre_temperature": 4.085901000000035, "dist": "39774.6444262", "temperature": 3.160852000000034, "minimum_temperature_at_2_metres": 3.6349730000000022, "timestamp": "2021-02-15T00:00:00+00:00", "v_component_of_wind_gust": 8.003021, "total_water_precipitation": 0.050781, "relative_humidity": 78.538933, "u_component_of_wind_gust": 4.443573, "wind_speed_gust": 9.160124, "position": [47.5, 5.5], "forecast": "2021-02-15T15:00:00+00:00", "maximum_temperature_at_2_metres": 4.364618000000007, "total_cloud_cover": 97.0, "downward_long_wave_radiation_flux": 15416859.0}, "geometry": {"type": "Point", "coordinates": [5.5, 47.5]}, "record_timestamp": "2021-02-15T00:00:00+00:00"}, {"datasetid": "arpege-05-sp1_sp2", "recordid": "arpege_05_sp1_sp2_lastgrib20-2081181", "fields": {"2_metre_dewpoint_temperature": 1.2329960000000142, "downward_short_wave_radiation_flux": 3508224.0, "2_metre_temperature": 2.606104000000016, "dist": "39774.6444262", "temperature": 1.477563000000032, "minimum_temperature_at_2_metres": 2.552271000000019, "timestamp": "2021-02-15T00:00:00+00:00", "v_component_of_wind_gust": 8.338425, "total_water_precipitation": 0.470703, "relative_humidity": 90.629265, "u_component_of_wind_gust": 3.987442, "wind_speed_gust": 9.24342, "position": [47.5, 5.5], "forecast": "2021-02-15T21:00:00+00:00", "maximum_temperature_at_2_metres": 2.9872680000000287, "total_cloud_cover": 100.0, "downward_long_wave_radiation_flux": 21814536.0}, "geometry": {"type": "Point", "coordinates": [5.5, 47.5]}, "record_timestamp": "2021-02-15T00:00:00+00:00"}, {"datasetid": "arpege-05-sp1_sp2", "recordid": "arpege_05_sp1_sp2_lastgrib20-2081188", "fields": {"2_metre_dewpoint_temperature": 5.849207000000035, "downward_short_wave_radiation_flux": 11894784.0, "2_metre_temperature": 6.714135999999996, "dist": "39774.6444262", "temperature": 5.300745000000006, "minimum_temperature_at_2_metres": 6.737024000000019, "timestamp": "2021-02-15T00:00:00+00:00", "v_component_of_wind_gust": 7.922043, "total_water_precipitation": 0.523438, "relative_humidity": 94.176025, "u_component_of_wind_gust": 3.664597, "wind_speed_gust": 8.719222, "position": [47.5, 5.5], "forecast": "2021-02-16T18:00:00+00:00", "maximum_temperature_at_2_metres": 9.580591000000027, "total_cloud_cover": 75.0, "downward_long_wave_radiation_flux": 43557984.0}, "geometry": {"type": "Point", "coordinates": [5.5, 47.5]}, "record_timestamp": "2021-02-15T00:00:00+00:00"}, {"datasetid": "arpege-05-sp1_sp2", "recordid": "arpege_05_sp1_sp2_lastgrib20-2081195", "fields": {"2_metre_dewpoint_temperature": 6.667871000000048, "downward_short_wave_radiation_flux": 18788352.0, "2_metre_temperature": 9.938135000000045, "dist": "39774.6444262", "temperature": 10.532190000000014, "minimum_temperature_at_2_metres": 7.5505620000000135, "timestamp": "2021-02-15T00:00:00+00:00", "v_component_of_wind_gust": 4.060837, "total_water_precipitation": 4.644531, "relative_humidity": 80.133156, "u_component_of_wind_gust": 2.53688, "wind_speed_gust": 4.791923, "position": [47.5, 5.5], "forecast": "2021-02-17T15:00:00+00:00", "maximum_temperature_at_2_metres": 9.929163000000017, "total_cloud_cover": 57.0, "downward_long_wave_radiation_flux": 68104624.0}, "geometry": {"type": "Point", "coordinates": [5.5, 47.5]}, "record_timestamp": "2021-02-15T00:00:00+00:00"}, {"datasetid": "arpege-05-sp1_sp2", "recordid": "arpege_05_sp1_sp2_lastgrib20-2081198", "fields": {"2_metre_dewpoint_temperature": -0.5552119999999832, "downward_short_wave_radiation_flux": 19509248.0, "2_metre_temperature": -0.5430049999999937, "dist": "39774.6444262", "temperature": -0.41953099999994947, "minimum_temperature_at_2_metres": -0.5468809999999849, "timestamp": "2021-02-15T00:00:00+00:00", "v_component_of_wind_gust": -1.28656, "total_water_precipitation": 4.648438, "relative_humidity": 99.960823, "u_component_of_wind_gust": 0.415939, "wind_speed_gust": 1.351424, "position": [47.5, 5.5], "forecast": "2021-02-18T00:00:00+00:00", "maximum_temperature_at_2_metres": 1.6248410000000035, "total_cloud_cover": 100.0, "downward_long_wave_radiation_flux": 76471984.0}, "geometry": {"type": "Point", "coordinates": [5.5, 47.5]}, "record_timestamp": "2021-02-15T00:00:00+00:00"}, {"datasetid": "arpege-05-sp1_sp2", "recordid": "arpege_05_sp1_sp2_lastgrib20-2081182", "fields": {"2_metre_dewpoint_temperature": 1.2600950000000353, "downward_short_wave_radiation_flux": 3508224.0, "2_metre_temperature": 2.4207700000000045, "dist": "39774.6444262", "temperature": 1.4677670000000376, "minimum_temperature_at_2_metres": 2.4324890000000323, "timestamp": "2021-02-15T00:00:00+00:00", "v_component_of_wind_gust": 7.588501, "total_water_precipitation": 0.472656, "relative_humidity": 92.079651, "u_component_of_wind_gust": 4.503601, "wind_speed_gust": 8.821295, "position": [47.5, 5.5], "forecast": "2021-02-16T00:00:00+00:00", "maximum_temperature_at_2_metres": 2.577997000000039, "total_cloud_cover": 97.0, "downward_long_wave_radiation_flux": 24958088.0}, "geometry": {"type": "Point", "coordinates": [5.5, 47.5]}, "record_timestamp": "2021-02-15T00:00:00+00:00"}, {"datasetid": "arpege-05-sp1_sp2", "recordid": "arpege_05_sp1_sp2_lastgrib20-2081185", "fields": {"2_metre_dewpoint_temperature": 2.6252080000000433, "downward_short_wave_radiation_flux": 4121600.0, "2_metre_temperature": 3.624780000000044, "dist": "39774.6444262", "temperature": 3.0966740000000073, "minimum_temperature_at_2_metres": 1.9146060000000489, "timestamp": "2021-02-15T00:00:00+00:00", "v_component_of_wind_gust": 6.713043, "total_water_precipitation": 0.519531, "relative_humidity": 93.171043, "u_component_of_wind_gust": 2.320862, "wind_speed_gust": 7.095191, "position": [47.5, 5.5], "forecast": "2021-02-16T09:00:00+00:00", "maximum_temperature_at_2_metres": 3.6254519999999957, "total_cloud_cover": 99.5, "downward_long_wave_radiation_flux": 34283340.0}, "geometry": {"type": "Point", "coordinates": [5.5, 47.5]}, "record_timestamp": "2021-02-15T00:00:00+00:00"}, {"datasetid": "arpege-05-sp1_sp2", "recordid": "arpege_05_sp1_sp2_lastgrib20-2081189", "fields": {"2_metre_dewpoint_temperature": 5.67891800000001, "downward_short_wave_radiation_flux": 11894784.0, "2_metre_temperature": 6.215814000000023, "dist": "39774.6444262", "temperature": 5.484491000000048, "minimum_temperature_at_2_metres": 6.172844999999995, "timestamp": "2021-02-15T00:00:00+00:00", "v_component_of_wind_gust": 7.971939, "total_water_precipitation": 0.734375, "relative_humidity": 96.349167, "u_component_of_wind_gust": 4.769302, "wind_speed_gust": 9.291804, "position": [47.5, 5.5], "forecast": "2021-02-16T21:00:00+00:00", "maximum_temperature_at_2_metres": 6.695093000000043, "total_cloud_cover": 100.0, "downward_long_wave_radiation_flux": 46861856.0}, "geometry": {"type": "Point", "coordinates": [5.5, 47.5]}, "record_timestamp": "2021-02-15T00:00:00+00:00"}, {"datasetid": "arpege-05-sp1_sp2", "recordid": "arpege_05_sp1_sp2_lastgrib20-2081199", "fields": {"2_metre_dewpoint_temperature": -0.8395139999999515, "downward_short_wave_radiation_flux": 19509248.0, "2_metre_temperature": -0.8044799999999555, "dist": "39774.6444262", "temperature": -0.3312129999999911, "minimum_temperature_at_2_metres": -1.082952999999975, "timestamp": "2021-02-15T00:00:00+00:00", "v_component_of_wind_gust": -0.409943, "total_water_precipitation": 4.648438, "relative_humidity": 99.812485, "u_component_of_wind_gust": 0.21611, "wind_speed_gust": 0.45423, "position": [47.5, 5.5], "forecast": "2021-02-18T03:00:00+00:00", "maximum_temperature_at_2_metres": -0.6012329999999793, "total_cloud_cover": 100.0, "downward_long_wave_radiation_flux": 79598208.0}, "geometry": {"type": "Point", "coordinates": [5.5, 47.5]}, "record_timestamp": "2021-02-15T00:00:00+00:00"}, {"datasetid": "arpege-05-sp1_sp2", "recordid": "arpege_05_sp1_sp2_lastgrib20-2081207", "fields": {"2_metre_dewpoint_temperature": 0.35766000000000986, "downward_short_wave_radiation_flux": 24969216.0, "2_metre_temperature": 0.3598269999999957, "dist": "39774.6444262", "temperature": 0.957727000000034, "minimum_temperature_at_2_metres": -1.0609499999999912, "timestamp": "2021-02-15T00:00:00+00:00", "v_component_of_wind_gust": 0.8815, "total_water_precipitation": 9.75, "relative_humidity": 99.988068, "u_component_of_wind_gust": -0.13829, "wind_speed_gust": 0.883343, "position": [47.5, 5.5], "forecast": "2021-02-19T06:00:00+00:00", "maximum_temperature_at_2_metres": 11.06991000000005, "total_cloud_cover": 100.0, "downward_long_wave_radiation_flux": 108509216.0}, "geometry": {"type": "Point", "coordinates": [5.5, 47.5]}, "record_timestamp": "2021-02-15T00:00:00+00:00"}, {"datasetid": "arpege-05-sp1_sp2", "recordid": "arpege_05_sp1_sp2_lastgrib20-2081177", "fields": {"2_metre_dewpoint_temperature": -2.551305999999954, "downward_short_wave_radiation_flux": 142848.0, "2_metre_temperature": 1.2726070000000504, "dist": "39774.6444262", "temperature": 0.4425899999999956, "minimum_temperature_at_2_metres": 0.4845210000000293, "timestamp": "2021-02-15T00:00:00+00:00", "v_component_of_wind_gust": 9.016205, "total_water_precipitation": 0.025391, "relative_humidity": 73.651413, "u_component_of_wind_gust": 3.15657, "wind_speed_gust": 9.560608, "position": [47.5, 5.5], "forecast": "2021-02-15T09:00:00+00:00", "maximum_temperature_at_2_metres": 1.2776730000000498, "total_cloud_cover": 100.0, "downward_long_wave_radiation_flux": 8948830.0}, "geometry": {"type": "Point", "coordinates": [5.5, 47.5]}, "record_timestamp": "2021-02-15T00:00:00+00:00"}, {"datasetid": "arpege-05-sp1_sp2", "recordid": "arpege_05_sp1_sp2_lastgrib20-2081190", "fields": {"2_metre_dewpoint_temperature": 5.591516000000013, "downward_short_wave_radiation_flux": 11894784.0, "2_metre_temperature": 5.877770999999996, "dist": "39774.6444262", "temperature": 5.304315000000031, "minimum_temperature_at_2_metres": 5.881677000000025, "timestamp": "2021-02-15T00:00:00+00:00", "v_component_of_wind_gust": 5.900253, "total_water_precipitation": 4.371094, "relative_humidity": 98.072525, "u_component_of_wind_gust": 4.374634, "wind_speed_gust": 7.347094, "position": [47.5, 5.5], "forecast": "2021-02-17T00:00:00+00:00", "maximum_temperature_at_2_metres": 6.264917000000025, "total_cloud_cover": 100.0, "downward_long_wave_radiation_flux": 50512072.0}, "geometry": {"type": "Point", "coordinates": [5.5, 47.5]}, "record_timestamp": "2021-02-15T00:00:00+00:00"}, {"datasetid": "arpege-05-sp1_sp2", "recordid": "arpege_05_sp1_sp2_lastgrib20-2081201", "fields": {"2_metre_dewpoint_temperature": 1.3258000000000152, "downward_short_wave_radiation_flux": 20209664.0, "2_metre_temperature": 1.9678279999999972, "dist": "39774.6444262", "temperature": 2.743188000000032, "minimum_temperature_at_2_metres": -0.6669069999999806, "timestamp": "2021-02-15T00:00:00+00:00", "v_component_of_wind_gust": -0.107727, "total_water_precipitation": 4.648438, "relative_humidity": 95.370041, "u_component_of_wind_gust": -0.121094, "wind_speed_gust": 0.177628, "position": [47.5, 5.5], "forecast": "2021-02-18T09:00:00+00:00", "maximum_temperature_at_2_metres": 1.9859560000000442, "total_cloud_cover": 95.5, "downward_long_wave_radiation_flux": 85773088.0}, "geometry": {"type": "Point", "coordinates": [5.5, 47.5]}, "record_timestamp": "2021-02-15T00:00:00+00:00"}, {"datasetid": "arpege-05-sp1_sp2", "recordid": "arpege_05_sp1_sp2_lastgrib20-2081202", "fields": {"2_metre_dewpoint_temperature": 6.963220000000035, "downward_short_wave_radiation_flux": 22280192.0, "2_metre_temperature": 9.525720000000035, "dist": "39774.6444262", "temperature": 9.11776100000003, "timestamp": "2021-02-15T00:00:00+00:00", "v_component_of_wind_gust": 10.927124, "total_water_precipitation": 4.664063, "relative_humidity": 84.068161, "u_component_of_wind_gust": 4.368927, "wind_speed_gust": 11.761245, "position": [47.5, 5.5], "forecast": "2021-02-18T12:00:00+00:00", "downward_long_wave_radiation_flux": 89115872.0, "total_cloud_cover": 100.0}, "geometry": {"type": "Point", "coordinates": [5.5, 47.5]}, "record_timestamp": "2021-02-15T00:00:00+00:00"}, {"datasetid": "arpege-05-sp1_sp2", "recordid": "arpege_05_sp1_sp2_lastgrib20-2081183", "fields": {"2_metre_dewpoint_temperature": 2.394067000000007, "downward_short_wave_radiation_flux": 3508224.0, "2_metre_temperature": 3.0770200000000045, "dist": "39774.6444262", "temperature": 2.2142580000000294, "minimum_temperature_at_2_metres": 2.439661000000001, "timestamp": "2021-02-15T00:00:00+00:00", "v_component_of_wind_gust": 6.550201, "total_water_precipitation": 0.521484, "relative_humidity": 95.358986, "u_component_of_wind_gust": 2.921173, "wind_speed_gust": 7.171514, "position": [47.5, 5.5], "forecast": "2021-02-16T03:00:00+00:00", "maximum_temperature_at_2_metres": 3.0731140000000323, "total_cloud_cover": 87.0, "downward_long_wave_radiation_flux": 28399480.0}, "geometry": {"type": "Point", "coordinates": [5.5, 47.5]}, "record_timestamp": "2021-02-15T00:00:00+00:00"}, {"datasetid": "arpege-05-sp1_sp2", "recordid": "arpege_05_sp1_sp2_lastgrib20-2081186", "fields": {"2_metre_dewpoint_temperature": 5.925745000000006, "downward_short_wave_radiation_flux": 7961600.0, "2_metre_temperature": 8.159235000000024, "dist": "39774.6444262", "temperature": 8.810571000000039, "minimum_temperature_at_2_metres": 3.5864500000000135, "timestamp": "2021-02-15T00:00:00+00:00", "v_component_of_wind_gust": 9.240005, "total_water_precipitation": 0.523438, "relative_humidity": 85.822884, "u_component_of_wind_gust": 4.326187, "wind_speed_gust": 10.201542, "position": [47.5, 5.5], "forecast": "2021-02-16T12:00:00+00:00", "maximum_temperature_at_2_metres": 8.149622000000022, "total_cloud_cover": 94.5, "downward_long_wave_radiation_flux": 37352152.0}, "geometry": {"type": "Point", "coordinates": [5.5, 47.5]}, "record_timestamp": "2021-02-15T00:00:00+00:00"}, {"datasetid": "arpege-05-sp1_sp2", "recordid": "arpege_05_sp1_sp2_lastgrib20-2081204", "fields": {"2_metre_dewpoint_temperature": 8.136682000000008, "downward_short_wave_radiation_flux": 24969216.0, "2_metre_temperature": 8.676569000000029, "dist": "39774.6444262", "temperature": 8.15249, "minimum_temperature_at_2_metres": -0.7874509999999759, "timestamp": "2021-02-15T00:00:00+00:00", "v_component_of_wind_gust": 11.439148, "total_water_precipitation": 8.28125, "relative_humidity": 96.488831, "u_component_of_wind_gust": 6.477097, "wind_speed_gust": 13.147639, "position": [47.5, 5.5], "forecast": "2021-02-18T18:00:00+00:00", "maximum_temperature_at_2_metres": 11.343469000000027, "total_cloud_cover": 100.0, "downward_long_wave_radiation_flux": 96074464.0}, "geometry": {"type": "Point", "coordinates": [5.5, 47.5]}, "record_timestamp": "2021-02-15T00:00:00+00:00"}, {"datasetid": "arpege-05-sp1_sp2", "recordid": "arpege_05_sp1_sp2_lastgrib20-2081184", "fields": {"2_metre_dewpoint_temperature": 1.5815060000000472, "downward_short_wave_radiation_flux": 3508224.0, "2_metre_temperature": 2.156030000000044, "dist": "39774.6444262", "temperature": 0.9449710000000096, "minimum_temperature_at_2_metres": 2.1734860000000253, "timestamp": "2021-02-15T00:00:00+00:00", "v_component_of_wind_gust": 5.926224, "total_water_precipitation": 0.523438, "relative_humidity": 95.805428, "u_component_of_wind_gust": 2.594238, "wind_speed_gust": 6.483536, "position": [47.5, 5.5], "forecast": "2021-02-16T06:00:00+00:00", "maximum_temperature_at_2_metres": 3.1013430000000426, "total_cloud_cover": 96.5, "downward_long_wave_radiation_flux": 31362964.0}, "geometry": {"type": "Point", "coordinates": [5.5, 47.5]}, "record_timestamp": "2021-02-15T00:00:00+00:00"}, {"datasetid": "arpege-05-sp1_sp2", "recordid": "arpege_05_sp1_sp2_lastgrib20-2081187", "fields": {"2_metre_dewpoint_temperature": 7.335260000000005, "downward_short_wave_radiation_flux": 11447296.0, "2_metre_temperature": 9.667810000000031, "dist": "39774.6444262", "temperature": 9.181848000000002, "minimum_temperature_at_2_metres": 8.362817000000007, "timestamp": "2021-02-15T00:00:00+00:00", "v_component_of_wind_gust": 8.686279, "total_water_precipitation": 0.523438, "relative_humidity": 85.286552, "u_component_of_wind_gust": 4.948715, "wind_speed_gust": 9.99703, "position": [47.5, 5.5], "forecast": "2021-02-16T15:00:00+00:00", "maximum_temperature_at_2_metres": 9.721033000000034, "total_cloud_cover": 100.0, "downward_long_wave_radiation_flux": 40541232.0}, "geometry": {"type": "Point", "coordinates": [5.5, 47.5]}, "record_timestamp": "2021-02-15T00:00:00+00:00"}, {"datasetid": "arpege-05-sp1_sp2", "recordid": "arpege_05_sp1_sp2_lastgrib20-2081191", "fields": {"2_metre_dewpoint_temperature": 5.338953000000004, "downward_short_wave_radiation_flux": 11894784.0, "2_metre_temperature": 5.472559000000047, "dist": "39774.6444262", "temperature": 5.083856000000026, "minimum_temperature_at_2_metres": 5.474512000000004, "timestamp": "2021-02-15T00:00:00+00:00", "v_component_of_wind_gust": 5.534332, "total_water_precipitation": 4.628906, "relative_humidity": 99.165337, "u_component_of_wind_gust": 4.110565, "wind_speed_gust": 6.896277, "position": [47.5, 5.5], "forecast": "2021-02-17T03:00:00+00:00", "maximum_temperature_at_2_metres": 5.789972000000034, "total_cloud_cover": 100.0, "downward_long_wave_radiation_flux": 54198900.0}, "geometry": {"type": "Point", "coordinates": [5.5, 47.5]}, "record_timestamp": "2021-02-15T00:00:00+00:00"}, {"datasetid": "arpege-05-sp1_sp2", "recordid": "arpege_05_sp1_sp2_lastgrib20-2081205", "fields": {"2_metre_dewpoint_temperature": 5.788416000000041, "downward_short_wave_radiation_flux": 24969216.0, "2_metre_temperature": 7.200769000000037, "dist": "39774.6444262", "temperature": 6.29445800000002, "minimum_temperature_at_2_metres": -0.7289179999999646, "timestamp": "2021-02-15T00:00:00+00:00", "v_component_of_wind_gust": 4.130066, "total_water_precipitation": 9.734375, "relative_humidity": 90.681442, "u_component_of_wind_gust": 6.036896, "wind_speed_gust": 7.323143, "position": [47.5, 5.5], "forecast": "2021-02-18T21:00:00+00:00", "maximum_temperature_at_2_metres": 11.402307000000008, "total_cloud_cover": 66.5, "downward_long_wave_radiation_flux": 99711568.0}, "geometry": {"type": "Point", "coordinates": [5.5, 47.5]}, "record_timestamp": "2021-02-15T00:00:00+00:00"}, {"datasetid": "arpege-05-sp1_sp2", "recordid": "arpege_05_sp1_sp2_lastgrib20-2081174", "fields": {"2_metre_dewpoint_temperature": -3.5951900000000023, "2_metre_temperature": -1.3616700000000037, "dist": "39774.6444262", "temperature": -1.959874999999954, "timestamp": "2021-02-15T00:00:00+00:00", "forecast": "2021-02-15T00:00:00+00:00", "relative_humidity": 82.854233, "position": [47.5, 5.5], "total_cloud_cover": 100.0}, "geometry": {"type": "Point", "coordinates": [5.5, 47.5]}, "record_timestamp": "2021-02-15T00:00:00+00:00"}, {"datasetid": "arpege-05-sp1_sp2", "recordid": "arpege_05_sp1_sp2_lastgrib20-2081176", "fields": {"2_metre_dewpoint_temperature": -3.5785889999999654, "downward_short_wave_radiation_flux": 0.0, "2_metre_temperature": 0.5899600000000191, "dist": "39774.6444262", "temperature": -0.6044069999999806, "minimum_temperature_at_2_metres": -0.585790999999972, "timestamp": "2021-02-15T00:00:00+00:00", "v_component_of_wind_gust": 7.786652, "total_water_precipitation": 0.006836, "relative_humidity": 71.113014, "u_component_of_wind_gust": 3.237473, "wind_speed_gust": 8.431334, "position": [47.5, 5.5], "forecast": "2021-02-15T06:00:00+00:00", "maximum_temperature_at_2_metres": 0.5762880000000337, "total_cloud_cover": 100.0, "downward_long_wave_radiation_flux": 5842121.0}, "geometry": {"type": "Point", "coordinates": [5.5, 47.5]}, "record_timestamp": "2021-02-15T00:00:00+00:00"}, {"datasetid": "arpege-05-sp1_sp2", "recordid": "arpege_05_sp1_sp2_lastgrib20-2081192", "fields": {"2_metre_dewpoint_temperature": 4.405511000000047, "downward_short_wave_radiation_flux": 11894784.0, "2_metre_temperature": 4.494348000000002, "dist": "39774.6444262", "temperature": 4.139978000000042, "minimum_temperature_at_2_metres": 4.491968000000043, "timestamp": "2021-02-15T00:00:00+00:00", "v_component_of_wind_gust": 5.014191, "total_water_precipitation": 4.632813, "relative_humidity": 99.519905, "u_component_of_wind_gust": 1.953491, "wind_speed_gust": 5.38589, "position": [47.5, 5.5], "forecast": "2021-02-17T06:00:00+00:00", "maximum_temperature_at_2_metres": 5.473596000000043, "total_cloud_cover": 93.0, "downward_long_wave_radiation_flux": 57806752.0}, "geometry": {"type": "Point", "coordinates": [5.5, 47.5]}, "record_timestamp": "2021-02-15T00:00:00+00:00"}, {"datasetid": "arpege-05-sp1_sp2", "recordid": "arpege_05_sp1_sp2_lastgrib20-2081200", "fields": {"2_metre_dewpoint_temperature": -0.7656619999999634, "downward_short_wave_radiation_flux": 19509248.0, "2_metre_temperature": -0.7324889999999868, "dist": "39774.6444262", "temperature": -0.4463259999999991, "minimum_temperature_at_2_metres": -0.8259029999999825, "timestamp": "2021-02-15T00:00:00+00:00", "v_component_of_wind_gust": -0.491211, "total_water_precipitation": 4.640625, "relative_humidity": 99.605637, "u_component_of_wind_gust": -1.001511, "wind_speed_gust": 1.09608, "position": [47.5, 5.5], "forecast": "2021-02-18T06:00:00+00:00", "maximum_temperature_at_2_metres": -0.5809689999999819, "total_cloud_cover": 99.5, "downward_long_wave_radiation_flux": 82694416.0}, "geometry": {"type": "Point", "coordinates": [5.5, 47.5]}, "record_timestamp": "2021-02-15T00:00:00+00:00"}], "facet_groups": [{"facets": [{"count": 102, "path": "2021", "state": "displayed", "name": "2021"}], "name": "forecast"}]}