{"nhits": 72, "parameters": {"dataset": ["arpege-05-sp1_sp2"], "timezone": "UTC", "rows": 10000, "start": 0, "format": "json", "geofilter.distance": ["48.8566,2.35222,40000"], "facet": ["forecast"]}, "records": [{"datasetid": "arpege-05-sp1_sp2", "recordid": "arpege_05_sp1_sp2_lastgrib20-2125626", "fields": {"2_metre_dewpoint_temperature": 0.7689150000000495, "downward_short_wave_radiation_flux": 2590720.0, "2_metre_temperature": 1.8053220000000465, "dist": "19256.4557757", "temperature": 1.0393310000000042, "minimum_temperature_at_2_metres": 0.6590820000000122, "timestamp": "2021-02-14T12:00:00+00:00", "v_component_of_wind_gust": 8.052856, "total_water_precipitation": 0.712891, "relative_humidity": 92.925209, "u_component_of_wind_gust": 0.37532, "wind_speed_gust": 8.064727, "position": [49.0, 2.5], "forecast": "2021-02-15T06:00:00+00:00", "maximum_temperature_at_2_metres": 1.7947020000000293, "total_cloud_cover": 100.0, "downward_long_wave_radiation_flux": 18627304.0}, "geometry": {"type": "Point", "coordinates": [2.5, 49.0]}, "record_timestamp": "2021-02-14T12:00:00+00:00"}, {"datasetid": "arpege-05-sp1_sp2", "recordid": "arpege_05_sp1_sp2_lastgrib20-2125641", "fields": {"2_metre_dewpoint_temperature": 5.043237000000033, "downward_short_wave_radiation_flux": 11556864.0, "2_metre_temperature": 5.383600000000001, "dist": "19256.4557757", "temperature": 4.560510000000022, "minimum_temperature_at_2_metres": 4.579675000000009, "timestamp": "2021-02-14T12:00:00+00:00", "v_component_of_wind_gust": 4.847931, "total_water_precipitation": 5.421875, "relative_humidity": 97.644333, "u_component_of_wind_gust": 4.919693, "wind_speed_gust": 6.902945, "position": [49.0, 2.5], "forecast": "2021-02-17T03:00:00+00:00", "maximum_temperature_at_2_metres": 5.3985530000000495, "total_cloud_cover": 100.0, "downward_long_wave_radiation_flux": 68537312.0}, "geometry": {"type": "Point", "coordinates": [2.5, 49.0]}, "record_timestamp": "2021-02-14T12:00:00+00:00"}, {"datasetid": "arpege-05-sp1_sp2", "recordid": "arpege_05_sp1_sp2_lastgrib20-2125646", "fields": {"2_metre_dewpoint_temperature": 6.295068000000015, "downward_short_wave_radiation_flux": 15114240.0, "2_metre_temperature": 7.673303000000033, "dist": "19256.4557757", "temperature": 5.9251650000000495, "minimum_temperature_at_2_metres": 7.653772000000004, "timestamp": "2021-02-14T12:00:00+00:00", "v_component_of_wind_gust": 8.578979, "total_water_precipitation": 5.835938, "relative_humidity": 91.132179, "u_component_of_wind_gust": 1.794464, "wind_speed_gust": 8.767808, "position": [49.0, 2.5], "forecast": "2021-02-17T18:00:00+00:00", "maximum_temperature_at_2_metres": 9.027002000000039, "total_cloud_cover": 84.5, "downward_long_wave_radiation_flux": 86181232.0}, "geometry": {"type": "Point", "coordinates": [2.5, 49.0]}, "record_timestamp": "2021-02-14T12:00:00+00:00"}, {"datasetid": "arpege-05-sp1_sp2", "recordid": "arpege_05_sp1_sp2_lastgrib20-2125647", "fields": {"2_metre_dewpoint_temperature": 5.659143000000029, "downward_short_wave_radiation_flux": 15114240.0, "2_metre_temperature": 7.399347000000034, "dist": "19256.4557757", "temperature": 5.319116000000008, "minimum_temperature_at_2_metres": 7.036035000000027, "timestamp": "2021-02-14T12:00:00+00:00", "v_component_of_wind_gust": 11.198883, "total_water_precipitation": 5.84375, "relative_humidity": 88.769432, "u_component_of_wind_gust": -0.028183, "wind_speed_gust": 11.203854, "position": [49.0, 2.5], "forecast": "2021-02-17T21:00:00+00:00", "maximum_temperature_at_2_metres": 7.559900000000027, "total_cloud_cover": 90.5, "downward_long_wave_radiation_flux": 89202896.0}, "geometry": {"type": "Point", "coordinates": [2.5, 49.0]}, "record_timestamp": "2021-02-14T12:00:00+00:00"}, {"datasetid": "arpege-05-sp1_sp2", "recordid": "arpege_05_sp1_sp2_lastgrib20-2125650", "fields": {"2_metre_dewpoint_temperature": 6.813257000000021, "downward_short_wave_radiation_flux": 15114240.0, "2_metre_temperature": 8.12832000000003, "dist": "19256.4557757", "temperature": 6.956079000000045, "minimum_temperature_at_2_metres": 6.837183000000039, "timestamp": "2021-02-14T12:00:00+00:00", "v_component_of_wind_gust": 10.748169, "total_water_precipitation": 11.960938, "relative_humidity": 91.386551, "u_component_of_wind_gust": 10.04097, "wind_speed_gust": 14.711664, "position": [49.0, 2.5], "forecast": "2021-02-18T06:00:00+00:00", "maximum_temperature_at_2_metres": 8.11403800000005, "total_cloud_cover": 100.0, "downward_long_wave_radiation_flux": 99429920.0}, "geometry": {"type": "Point", "coordinates": [2.5, 49.0]}, "record_timestamp": "2021-02-14T12:00:00+00:00"}, {"datasetid": "arpege-05-sp1_sp2", "recordid": "arpege_05_sp1_sp2_lastgrib20-2125621", "fields": {"2_metre_dewpoint_temperature": -5.696935999999994, "downward_short_wave_radiation_flux": 2325760.0, "2_metre_temperature": 0.2920780000000036, "dist": "19256.4557757", "temperature": 0.5863889999999969, "minimum_temperature_at_2_metres": -0.967931999999962, "timestamp": "2021-02-14T12:00:00+00:00", "v_component_of_wind_gust": 6.041092, "total_water_precipitation": 0.0, "relative_humidity": 60.59626, "u_component_of_wind_gust": -6.233002, "wind_speed_gust": 8.680217, "position": [49.0, 2.5], "forecast": "2021-02-14T15:00:00+00:00", "maximum_temperature_at_2_metres": 0.31398900000004915, "total_cloud_cover": 100.0, "downward_long_wave_radiation_flux": 2861134.25}, "geometry": {"type": "Point", "coordinates": [2.5, 49.0]}, "record_timestamp": "2021-02-14T12:00:00+00:00"}, {"datasetid": "arpege-05-sp1_sp2", "recordid": "arpege_05_sp1_sp2_lastgrib20-2125625", "fields": {"2_metre_dewpoint_temperature": -0.9339359999999601, "downward_short_wave_radiation_flux": 2590720.0, "2_metre_temperature": 0.6412600000000452, "dist": "19256.4557757", "temperature": -0.04691199999996343, "minimum_temperature_at_2_metres": -0.40561499999995476, "timestamp": "2021-02-14T12:00:00+00:00", "v_component_of_wind_gust": 7.411804, "total_water_precipitation": 0.261719, "relative_humidity": 88.308823, "u_component_of_wind_gust": -3.227844, "wind_speed_gust": 8.084976, "position": [49.0, 2.5], "forecast": "2021-02-15T03:00:00+00:00", "maximum_temperature_at_2_metres": 0.6331120000000396, "total_cloud_cover": 99.5, "downward_long_wave_radiation_flux": 15177495.0}, "geometry": {"type": "Point", "coordinates": [2.5, 49.0]}, "record_timestamp": "2021-02-14T12:00:00+00:00"}, {"datasetid": "arpege-05-sp1_sp2", "recordid": "arpege_05_sp1_sp2_lastgrib20-2125628", "fields": {"2_metre_dewpoint_temperature": 1.8405089999999973, "downward_short_wave_radiation_flux": 3698688.0, "2_metre_temperature": 3.171045000000049, "dist": "19256.4557757", "temperature": 2.9379519999999957, "minimum_temperature_at_2_metres": 2.0452510000000075, "timestamp": "2021-02-14T12:00:00+00:00", "v_component_of_wind_gust": 7.982025, "total_water_precipitation": 1.488281, "relative_humidity": 91.021553, "u_component_of_wind_gust": 2.147079, "wind_speed_gust": 8.26896, "position": [49.0, 2.5], "forecast": "2021-02-15T12:00:00+00:00", "maximum_temperature_at_2_metres": 3.1653380000000197, "total_cloud_cover": 99.0, "downward_long_wave_radiation_flux": 25400868.0}, "geometry": {"type": "Point", "coordinates": [2.5, 49.0]}, "record_timestamp": "2021-02-14T12:00:00+00:00"}, {"datasetid": "arpege-05-sp1_sp2", "recordid": "arpege_05_sp1_sp2_lastgrib20-2125631", "fields": {"2_metre_dewpoint_temperature": 2.654749000000038, "downward_short_wave_radiation_flux": 5104640.0, "2_metre_temperature": 3.2117250000000013, "dist": "19256.4557757", "temperature": 2.2754150000000095, "minimum_temperature_at_2_metres": 3.073053000000016, "timestamp": "2021-02-14T12:00:00+00:00", "v_component_of_wind_gust": 5.34082, "total_water_precipitation": 4.097656, "relative_humidity": 96.170166, "u_component_of_wind_gust": 0.119003, "wind_speed_gust": 5.353325, "position": [49.0, 2.5], "forecast": "2021-02-15T21:00:00+00:00", "maximum_temperature_at_2_metres": 3.314783000000034, "total_cloud_cover": 93.0, "downward_long_wave_radiation_flux": 35934888.0}, "geometry": {"type": "Point", "coordinates": [2.5, 49.0]}, "record_timestamp": "2021-02-14T12:00:00+00:00"}, {"datasetid": "arpege-05-sp1_sp2", "recordid": "arpege_05_sp1_sp2_lastgrib20-2125638", "fields": {"2_metre_dewpoint_temperature": 5.865625000000023, "downward_short_wave_radiation_flux": 11556864.0, "2_metre_temperature": 6.374323000000004, "dist": "19256.4557757", "temperature": 5.251489000000049, "minimum_temperature_at_2_metres": 6.354791000000034, "timestamp": "2021-02-14T12:00:00+00:00", "v_component_of_wind_gust": 4.901199, "total_water_precipitation": 4.800781, "relative_humidity": 96.569168, "u_component_of_wind_gust": 4.121948, "wind_speed_gust": 6.413691, "position": [49.0, 2.5], "forecast": "2021-02-16T18:00:00+00:00", "maximum_temperature_at_2_metres": 7.48562000000004, "total_cloud_cover": 99.0, "downward_long_wave_radiation_flux": 57620748.0}, "geometry": {"type": "Point", "coordinates": [2.5, 49.0]}, "record_timestamp": "2021-02-14T12:00:00+00:00"}, {"datasetid": "arpege-05-sp1_sp2", "recordid": "arpege_05_sp1_sp2_lastgrib20-2125639", "fields": {"2_metre_dewpoint_temperature": 4.949762000000021, "downward_short_wave_radiation_flux": 11556864.0, "2_metre_temperature": 5.211938000000032, "dist": "19256.4557757", "temperature": 4.122369000000049, "minimum_temperature_at_2_metres": 5.222711000000004, "timestamp": "2021-02-14T12:00:00+00:00", "v_component_of_wind_gust": 3.461563, "total_water_precipitation": 5.234375, "relative_humidity": 98.169357, "u_component_of_wind_gust": 3.365509, "wind_speed_gust": 4.8344, "position": [49.0, 2.5], "forecast": "2021-02-16T21:00:00+00:00", "maximum_temperature_at_2_metres": 6.297540000000026, "total_cloud_cover": 93.5, "downward_long_wave_radiation_flux": 61254720.0}, "geometry": {"type": "Point", "coordinates": [2.5, 49.0]}, "record_timestamp": "2021-02-14T12:00:00+00:00"}, {"datasetid": "arpege-05-sp1_sp2", "recordid": "arpege_05_sp1_sp2_lastgrib20-2125654", "fields": {"2_metre_dewpoint_temperature": 5.126824999999997, "downward_short_wave_radiation_flux": 21245952.0, "2_metre_temperature": 6.397913000000017, "dist": "19256.4557757", "temperature": 5.574121000000048, "minimum_temperature_at_2_metres": 6.347955000000013, "timestamp": "2021-02-14T12:00:00+00:00", "v_component_of_wind_gust": 15.054901, "total_water_precipitation": 15.703125, "relative_humidity": 91.465302, "u_component_of_wind_gust": 1.677368, "wind_speed_gust": 15.145889, "position": [49.0, 2.5], "forecast": "2021-02-19T00:00:00+00:00", "maximum_temperature_at_2_metres": 9.613794000000041, "total_cloud_cover": 100.0, "downward_long_wave_radiation_flux": 119098832.0}, "geometry": {"type": "Point", "coordinates": [2.5, 49.0]}, "record_timestamp": "2021-02-14T12:00:00+00:00"}, {"datasetid": "arpege-05-sp1_sp2", "recordid": "arpege_05_sp1_sp2_lastgrib20-2125627", "fields": {"2_metre_dewpoint_temperature": 0.7788020000000415, "downward_short_wave_radiation_flux": 2690048.0, "2_metre_temperature": 1.9997800000000439, "dist": "19256.4557757", "temperature": 1.2923830000000294, "minimum_temperature_at_2_metres": 1.79445800000002, "timestamp": "2021-02-14T12:00:00+00:00", "v_component_of_wind_gust": 7.785583, "total_water_precipitation": 0.953125, "relative_humidity": 91.605858, "u_component_of_wind_gust": -0.761658, "wind_speed_gust": 7.834369, "position": [49.0, 2.5], "forecast": "2021-02-15T09:00:00+00:00", "maximum_temperature_at_2_metres": 1.9875729999999976, "total_cloud_cover": 99.0, "downward_long_wave_radiation_flux": 22009194.0}, "geometry": {"type": "Point", "coordinates": [2.5, 49.0]}, "record_timestamp": "2021-02-14T12:00:00+00:00"}, {"datasetid": "arpege-05-sp1_sp2", "recordid": "arpege_05_sp1_sp2_lastgrib20-2125630", "fields": {"2_metre_dewpoint_temperature": 2.709496999999999, "downward_short_wave_radiation_flux": 5104640.0, "2_metre_temperature": 3.3656860000000393, "dist": "19256.4557757", "temperature": 2.5975590000000466, "minimum_temperature_at_2_metres": 3.36178000000001, "timestamp": "2021-02-14T12:00:00+00:00", "v_component_of_wind_gust": 6.099899, "total_water_precipitation": 2.5, "relative_humidity": 95.43367, "u_component_of_wind_gust": 1.285263, "wind_speed_gust": 6.227373, "position": [49.0, 2.5], "forecast": "2021-02-15T18:00:00+00:00", "maximum_temperature_at_2_metres": 3.854150000000004, "total_cloud_cover": 100.0, "downward_long_wave_radiation_flux": 32434482.0}, "geometry": {"type": "Point", "coordinates": [2.5, 49.0]}, "record_timestamp": "2021-02-14T12:00:00+00:00"}, {"datasetid": "arpege-05-sp1_sp2", "recordid": "arpege_05_sp1_sp2_lastgrib20-2125632", "fields": {"2_metre_dewpoint_temperature": 1.620020000000011, "downward_short_wave_radiation_flux": 5105664.0, "2_metre_temperature": 1.9176270000000386, "dist": "19256.4557757", "temperature": 0.5542240000000334, "minimum_temperature_at_2_metres": 1.9245240000000194, "timestamp": "2021-02-14T12:00:00+00:00", "v_component_of_wind_gust": 4.652359, "total_water_precipitation": 4.097656, "relative_humidity": 97.767975, "u_component_of_wind_gust": -0.822754, "wind_speed_gust": 4.71544, "position": [49.0, 2.5], "forecast": "2021-02-16T00:00:00+00:00", "maximum_temperature_at_2_metres": 3.1792540000000145, "total_cloud_cover": 89.5, "downward_long_wave_radiation_flux": 39039232.0}, "geometry": {"type": "Point", "coordinates": [2.5, 49.0]}, "record_timestamp": "2021-02-14T12:00:00+00:00"}, {"datasetid": "arpege-05-sp1_sp2", "recordid": "arpege_05_sp1_sp2_lastgrib20-2125644", "fields": {"2_metre_dewpoint_temperature": 6.598657000000003, "downward_short_wave_radiation_flux": 12570624.0, "2_metre_temperature": 7.530023000000028, "dist": "19256.4557757", "temperature": 7.253870000000006, "minimum_temperature_at_2_metres": 5.201593000000003, "timestamp": "2021-02-14T12:00:00+00:00", "v_component_of_wind_gust": 11.112152, "total_water_precipitation": 5.835938, "relative_humidity": 93.787262, "u_component_of_wind_gust": 4.125259, "wind_speed_gust": 11.851309, "position": [49.0, 2.5], "forecast": "2021-02-17T12:00:00+00:00", "maximum_temperature_at_2_metres": 7.542810000000031, "total_cloud_cover": 99.0, "downward_long_wave_radiation_flux": 79498496.0}, "geometry": {"type": "Point", "coordinates": [2.5, 49.0]}, "record_timestamp": "2021-02-14T12:00:00+00:00"}, {"datasetid": "arpege-05-sp1_sp2", "recordid": "arpege_05_sp1_sp2_lastgrib20-2125645", "fields": {"2_metre_dewpoint_temperature": 7.1442499999999995, "downward_short_wave_radiation_flux": 14551040.0, "2_metre_temperature": 9.047357000000034, "dist": "19256.4557757", "temperature": 8.511987000000033, "minimum_temperature_at_2_metres": 7.596216000000027, "timestamp": "2021-02-14T12:00:00+00:00", "v_component_of_wind_gust": 10.380371, "total_water_precipitation": 5.835938, "relative_humidity": 87.871445, "u_component_of_wind_gust": 5.254639, "wind_speed_gust": 11.646478, "position": [49.0, 2.5], "forecast": "2021-02-17T15:00:00+00:00", "maximum_temperature_at_2_metres": 9.052454000000012, "total_cloud_cover": 100.0, "downward_long_wave_radiation_flux": 83081952.0}, "geometry": {"type": "Point", "coordinates": [2.5, 49.0]}, "record_timestamp": "2021-02-14T12:00:00+00:00"}, {"datasetid": "arpege-05-sp1_sp2", "recordid": "arpege_05_sp1_sp2_lastgrib20-2125622", "fields": {"2_metre_dewpoint_temperature": -3.5014099999999644, "downward_short_wave_radiation_flux": 2590208.0, "2_metre_temperature": -0.25198999999997795, "dist": "19256.4557757", "temperature": -1.2239139999999793, "minimum_temperature_at_2_metres": -0.25284399999998186, "timestamp": "2021-02-14T12:00:00+00:00", "v_component_of_wind_gust": 3.703369, "total_water_precipitation": 0.0, "relative_humidity": 76.206589, "u_component_of_wind_gust": -5.451843, "wind_speed_gust": 6.598134, "position": [49.0, 2.5], "forecast": "2021-02-14T18:00:00+00:00", "maximum_temperature_at_2_metres": 0.29210800000004156, "total_cloud_cover": 100.0, "downward_long_wave_radiation_flux": 5811602.0}, "geometry": {"type": "Point", "coordinates": [2.5, 49.0]}, "record_timestamp": "2021-02-14T12:00:00+00:00"}, {"datasetid": "arpege-05-sp1_sp2", "recordid": "arpege_05_sp1_sp2_lastgrib20-2125623", "fields": {"2_metre_dewpoint_temperature": -3.145879999999977, "downward_short_wave_radiation_flux": 2590720.0, "2_metre_temperature": -0.07791699999995672, "dist": "19256.4557757", "temperature": -1.105840999999998, "minimum_temperature_at_2_metres": -0.21878699999996343, "timestamp": "2021-02-14T12:00:00+00:00", "v_component_of_wind_gust": 5.903687, "total_water_precipitation": 0.0, "relative_humidity": 77.490883, "u_component_of_wind_gust": -4.976242, "wind_speed_gust": 7.716683, "position": [49.0, 2.5], "forecast": "2021-02-14T21:00:00+00:00", "maximum_temperature_at_2_metres": -0.02530500000000302, "total_cloud_cover": 100.0, "downward_long_wave_radiation_flux": 8811391.0}, "geometry": {"type": "Point", "coordinates": [2.5, 49.0]}, "record_timestamp": "2021-02-14T12:00:00+00:00"}, {"datasetid": "arpege-05-sp1_sp2", "recordid": "arpege_05_sp1_sp2_lastgrib20-2125636", "fields": {"2_metre_dewpoint_temperature": 4.900049000000024, "downward_short_wave_radiation_flux": 8941568.0, "2_metre_temperature": 6.2281430000000455, "dist": "19256.4557757", "temperature": 7.420525999999995, "minimum_temperature_at_2_metres": 2.406519000000003, "timestamp": "2021-02-14T12:00:00+00:00", "v_component_of_wind_gust": 8.921646, "total_water_precipitation": 4.097656, "relative_humidity": 91.227554, "u_component_of_wind_gust": 1.598892, "wind_speed_gust": 9.057547, "position": [49.0, 2.5], "forecast": "2021-02-16T12:00:00+00:00", "maximum_temperature_at_2_metres": 6.215723000000025, "total_cloud_cover": 95.5, "downward_long_wave_radiation_flux": 50586100.0}, "geometry": {"type": "Point", "coordinates": [2.5, 49.0]}, "record_timestamp": "2021-02-14T12:00:00+00:00"}, {"datasetid": "arpege-05-sp1_sp2", "recordid": "arpege_05_sp1_sp2_lastgrib20-2125655", "fields": {"2_metre_dewpoint_temperature": 8.645105000000001, "downward_short_wave_radiation_flux": 21245952.0, "2_metre_temperature": 9.587579000000005, "dist": "19256.4557757", "temperature": 8.801508000000013, "minimum_temperature_at_2_metres": 6.388940000000048, "timestamp": "2021-02-14T12:00:00+00:00", "v_component_of_wind_gust": 14.181198, "total_water_precipitation": 19.664063, "relative_humidity": 93.671371, "u_component_of_wind_gust": 8.181305, "wind_speed_gust": 16.365608, "position": [49.0, 2.5], "forecast": "2021-02-19T06:00:00+00:00", "maximum_temperature_at_2_metres": 9.654626000000007, "total_cloud_cover": 100.0, "downward_long_wave_radiation_flux": 126607696.0}, "geometry": {"type": "Point", "coordinates": [2.5, 49.0]}, "record_timestamp": "2021-02-14T12:00:00+00:00"}, {"datasetid": "arpege-05-sp1_sp2", "recordid": "arpege_05_sp1_sp2_lastgrib20-2125640", "fields": {"2_metre_dewpoint_temperature": 4.477013999999997, "downward_short_wave_radiation_flux": 11556864.0, "2_metre_temperature": 4.516382000000021, "dist": "19256.4557757", "temperature": 3.6706180000000472, "minimum_temperature_at_2_metres": 4.48864100000003, "timestamp": "2021-02-14T12:00:00+00:00", "v_component_of_wind_gust": 3.535904, "total_water_precipitation": 5.28125, "relative_humidity": 99.927155, "u_component_of_wind_gust": 2.398788, "wind_speed_gust": 4.280319, "position": [49.0, 2.5], "forecast": "2021-02-17T00:00:00+00:00", "maximum_temperature_at_2_metres": 5.190210000000036, "total_cloud_cover": 100.0, "downward_long_wave_radiation_flux": 64854816.0}, "geometry": {"type": "Point", "coordinates": [2.5, 49.0]}, "record_timestamp": "2021-02-14T12:00:00+00:00"}, {"datasetid": "arpege-05-sp1_sp2", "recordid": "arpege_05_sp1_sp2_lastgrib20-2125643", "fields": {"2_metre_dewpoint_temperature": 4.990076000000045, "downward_short_wave_radiation_flux": 11683840.0, "2_metre_temperature": 5.196069000000023, "dist": "19256.4557757", "temperature": 4.882227, "minimum_temperature_at_2_metres": 4.589960000000019, "timestamp": "2021-02-14T12:00:00+00:00", "v_component_of_wind_gust": 8.318527, "total_water_precipitation": 5.679688, "relative_humidity": 98.709061, "u_component_of_wind_gust": 2.322372, "wind_speed_gust": 8.640265, "position": [49.0, 2.5], "forecast": "2021-02-17T09:00:00+00:00", "maximum_temperature_at_2_metres": 5.189111000000025, "total_cloud_cover": 100.0, "downward_long_wave_radiation_flux": 75788352.0}, "geometry": {"type": "Point", "coordinates": [2.5, 49.0]}, "record_timestamp": "2021-02-14T12:00:00+00:00"}, {"datasetid": "arpege-05-sp1_sp2", "recordid": "arpege_05_sp1_sp2_lastgrib20-2125653", "fields": {"2_metre_dewpoint_temperature": 5.6802000000000135, "downward_short_wave_radiation_flux": 21245952.0, "2_metre_temperature": 8.182092000000011, "dist": "19256.4557757", "temperature": 6.743065999999999, "minimum_temperature_at_2_metres": 6.814294000000018, "timestamp": "2021-02-14T12:00:00+00:00", "v_component_of_wind_gust": 9.063522, "total_water_precipitation": 13.539063, "relative_humidity": 84.265526, "u_component_of_wind_gust": 6.974899, "wind_speed_gust": 11.449756, "position": [49.0, 2.5], "forecast": "2021-02-18T18:00:00+00:00", "maximum_temperature_at_2_metres": 9.606042000000002, "total_cloud_cover": 94.5, "downward_long_wave_radiation_flux": 112565616.0}, "geometry": {"type": "Point", "coordinates": [2.5, 49.0]}, "record_timestamp": "2021-02-14T12:00:00+00:00"}, {"datasetid": "arpege-05-sp1_sp2", "recordid": "arpege_05_sp1_sp2_lastgrib20-2125620", "fields": {"2_metre_dewpoint_temperature": -8.725499999999954, "2_metre_temperature": -0.9107419999999706, "dist": "19256.4557757", "temperature": 2.9983760000000075, "timestamp": "2021-02-14T12:00:00+00:00", "forecast": "2021-02-14T12:00:00+00:00", "relative_humidity": 51.313564, "position": [49.0, 2.5], "total_cloud_cover": 100.0}, "geometry": {"type": "Point", "coordinates": [2.5, 49.0]}, "record_timestamp": "2021-02-14T12:00:00+00:00"}, {"datasetid": "arpege-05-sp1_sp2", "recordid": "arpege_05_sp1_sp2_lastgrib20-2125624", "fields": {"2_metre_dewpoint_temperature": -2.856420999999955, "downward_short_wave_radiation_flux": 2590720.0, "2_metre_temperature": -0.3780879999999911, "dist": "19256.4557757", "temperature": -1.1670899999999733, "minimum_temperature_at_2_metres": -0.40347900000000436, "timestamp": "2021-02-14T12:00:00+00:00", "v_component_of_wind_gust": 5.619019, "total_water_precipitation": 0.011719, "relative_humidity": 81.287117, "u_component_of_wind_gust": -4.008591, "wind_speed_gust": 6.914382, "position": [49.0, 2.5], "forecast": "2021-02-15T00:00:00+00:00", "maximum_temperature_at_2_metres": -0.07230199999997922, "total_cloud_cover": 99.0, "downward_long_wave_radiation_flux": 11865074.0}, "geometry": {"type": "Point", "coordinates": [2.5, 49.0]}, "record_timestamp": "2021-02-14T12:00:00+00:00"}, {"datasetid": "arpege-05-sp1_sp2", "recordid": "arpege_05_sp1_sp2_lastgrib20-2125634", "fields": {"2_metre_dewpoint_temperature": -0.24271199999998316, "downward_short_wave_radiation_flux": 5105664.0, "2_metre_temperature": 0.5765930000000026, "dist": "19256.4557757", "temperature": -0.8312129999999911, "minimum_temperature_at_2_metres": 0.479028000000028, "timestamp": "2021-02-14T12:00:00+00:00", "v_component_of_wind_gust": 6.077026, "total_water_precipitation": 4.097656, "relative_humidity": 94.000061, "u_component_of_wind_gust": -0.506973, "wind_speed_gust": 6.113611, "position": [49.0, 2.5], "forecast": "2021-02-16T06:00:00+00:00", "maximum_temperature_at_2_metres": 0.6742490000000316, "total_cloud_cover": 76.5, "downward_long_wave_radiation_flux": 44665296.0}, "geometry": {"type": "Point", "coordinates": [2.5, 49.0]}, "record_timestamp": "2021-02-14T12:00:00+00:00"}, {"datasetid": "arpege-05-sp1_sp2", "recordid": "arpege_05_sp1_sp2_lastgrib20-2125642", "fields": {"2_metre_dewpoint_temperature": 4.857141000000013, "downward_short_wave_radiation_flux": 11556864.0, "2_metre_temperature": 5.098657000000003, "dist": "19256.4557757", "temperature": 4.703271000000029, "minimum_temperature_at_2_metres": 5.103601000000026, "timestamp": "2021-02-14T12:00:00+00:00", "v_component_of_wind_gust": 6.821014, "total_water_precipitation": 5.492188, "relative_humidity": 98.290092, "u_component_of_wind_gust": 3.842987, "wind_speed_gust": 7.838324, "position": [49.0, 2.5], "forecast": "2021-02-17T06:00:00+00:00", "maximum_temperature_at_2_metres": 6.035059000000047, "total_cloud_cover": 93.5, "downward_long_wave_radiation_flux": 72212064.0}, "geometry": {"type": "Point", "coordinates": [2.5, 49.0]}, "record_timestamp": "2021-02-14T12:00:00+00:00"}, {"datasetid": "arpege-05-sp1_sp2", "recordid": "arpege_05_sp1_sp2_lastgrib20-2125652", "fields": {"2_metre_dewpoint_temperature": 5.772241000000008, "downward_short_wave_radiation_flux": 19009536.0, "2_metre_temperature": 8.680383000000006, "dist": "19256.4557757", "temperature": 8.337061000000006, "minimum_temperature_at_2_metres": 6.815851000000009, "timestamp": "2021-02-14T12:00:00+00:00", "v_component_of_wind_gust": 10.923599, "total_water_precipitation": 13.046875, "relative_humidity": 82.107834, "u_component_of_wind_gust": 13.038345, "wind_speed_gust": 17.006304, "position": [49.0, 2.5], "forecast": "2021-02-18T12:00:00+00:00", "maximum_temperature_at_2_metres": 8.670190000000048, "total_cloud_cover": 100.0, "downward_long_wave_radiation_flux": 105855520.0}, "geometry": {"type": "Point", "coordinates": [2.5, 49.0]}, "record_timestamp": "2021-02-14T12:00:00+00:00"}, {"datasetid": "arpege-05-sp1_sp2", "recordid": "arpege_05_sp1_sp2_lastgrib20-2125629", "fields": {"2_metre_dewpoint_temperature": 2.711938000000032, "downward_short_wave_radiation_flux": 5061632.0, "2_metre_temperature": 3.899438000000032, "dist": "19256.4557757", "temperature": 3.479150000000004, "minimum_temperature_at_2_metres": 3.1709840000000327, "timestamp": "2021-02-14T12:00:00+00:00", "v_component_of_wind_gust": 9.61644, "total_water_precipitation": 1.980469, "relative_humidity": 92.072586, "u_component_of_wind_gust": 1.702454, "wind_speed_gust": 9.767229, "position": [49.0, 2.5], "forecast": "2021-02-15T15:00:00+00:00", "maximum_temperature_at_2_metres": 4.2602170000000115, "total_cloud_cover": 100.0, "downward_long_wave_radiation_flux": 28824024.0}, "geometry": {"type": "Point", "coordinates": [2.5, 49.0]}, "record_timestamp": "2021-02-14T12:00:00+00:00"}, {"datasetid": "arpege-05-sp1_sp2", "recordid": "arpege_05_sp1_sp2_lastgrib20-2125633", "fields": {"2_metre_dewpoint_temperature": 0.3493590000000495, "downward_short_wave_radiation_flux": 5105664.0, "2_metre_temperature": 0.6436400000000049, "dist": "19256.4557757", "temperature": -0.7367919999999799, "minimum_temperature_at_2_metres": 0.6391849999999977, "timestamp": "2021-02-14T12:00:00+00:00", "v_component_of_wind_gust": 5.181168, "total_water_precipitation": 4.097656, "relative_humidity": 97.842773, "u_component_of_wind_gust": -1.228485, "wind_speed_gust": 5.341062, "position": [49.0, 2.5], "forecast": "2021-02-16T03:00:00+00:00", "maximum_temperature_at_2_metres": 1.8936400000000049, "total_cloud_cover": 68.0, "downward_long_wave_radiation_flux": 41880296.0}, "geometry": {"type": "Point", "coordinates": [2.5, 49.0]}, "record_timestamp": "2021-02-14T12:00:00+00:00"}, {"datasetid": "arpege-05-sp1_sp2", "recordid": "arpege_05_sp1_sp2_lastgrib20-2125635", "fields": {"2_metre_dewpoint_temperature": 1.0911800000000085, "downward_short_wave_radiation_flux": 5582848.0, "2_metre_temperature": 2.216852000000017, "dist": "19256.4557757", "temperature": 1.6286249999999995, "minimum_temperature_at_2_metres": 0.5707950000000324, "timestamp": "2021-02-14T12:00:00+00:00", "v_component_of_wind_gust": 7.782364, "total_water_precipitation": 4.097656, "relative_humidity": 92.296707, "u_component_of_wind_gust": 1.439392, "wind_speed_gust": 7.917887, "position": [49.0, 2.5], "forecast": "2021-02-16T09:00:00+00:00", "maximum_temperature_at_2_metres": 2.202997000000039, "total_cloud_cover": 66.0, "downward_long_wave_radiation_flux": 47549968.0}, "geometry": {"type": "Point", "coordinates": [2.5, 49.0]}, "record_timestamp": "2021-02-14T12:00:00+00:00"}, {"datasetid": "arpege-05-sp1_sp2", "recordid": "arpege_05_sp1_sp2_lastgrib20-2125637", "fields": {"2_metre_dewpoint_temperature": 6.2025090000000205, "downward_short_wave_radiation_flux": 11440128.0, "2_metre_temperature": 7.482996000000014, "dist": "19256.4557757", "temperature": 7.0164120000000025, "minimum_temperature_at_2_metres": 6.2270750000000135, "timestamp": "2021-02-14T12:00:00+00:00", "v_component_of_wind_gust": 9.014404, "total_water_precipitation": 4.097656, "relative_humidity": 91.630043, "u_component_of_wind_gust": 2.731049, "wind_speed_gust": 9.409502, "position": [49.0, 2.5], "forecast": "2021-02-16T15:00:00+00:00", "maximum_temperature_at_2_metres": 7.768884000000014, "total_cloud_cover": 100.0, "downward_long_wave_radiation_flux": 53934920.0}, "geometry": {"type": "Point", "coordinates": [2.5, 49.0]}, "record_timestamp": "2021-02-14T12:00:00+00:00"}, {"datasetid": "arpege-05-sp1_sp2", "recordid": "arpege_05_sp1_sp2_lastgrib20-2125648", "fields": {"2_metre_dewpoint_temperature": 5.791832999999997, "downward_short_wave_radiation_flux": 15114240.0, "2_metre_temperature": 7.08785400000005, "dist": "19256.4557757", "temperature": 5.764795000000049, "timestamp": "2021-02-14T12:00:00+00:00", "v_component_of_wind_gust": 10.976044, "total_water_precipitation": 5.859375, "relative_humidity": 91.395798, "u_component_of_wind_gust": 0.770233, "wind_speed_gust": 11.004652, "position": [49.0, 2.5], "forecast": "2021-02-18T00:00:00+00:00", "downward_long_wave_radiation_flux": 92319232.0, "total_cloud_cover": 99.0}, "geometry": {"type": "Point", "coordinates": [2.5, 49.0]}, "record_timestamp": "2021-02-14T12:00:00+00:00"}, {"datasetid": "arpege-05-sp1_sp2", "recordid": "arpege_05_sp1_sp2_lastgrib20-2125649", "fields": {"2_metre_dewpoint_temperature": 6.026880000000006, "downward_short_wave_radiation_flux": 15114240.0, "2_metre_temperature": 6.80159900000001, "dist": "19256.4557757", "temperature": 5.913110000000017, "minimum_temperature_at_2_metres": 6.827112, "timestamp": "2021-02-14T12:00:00+00:00", "v_component_of_wind_gust": 11.295135, "total_water_precipitation": 7.90625, "relative_humidity": 94.646309, "u_component_of_wind_gust": -2.896957, "wind_speed_gust": 11.662264, "position": [49.0, 2.5], "forecast": "2021-02-18T03:00:00+00:00", "maximum_temperature_at_2_metres": 7.657556, "total_cloud_cover": 100.0, "downward_long_wave_radiation_flux": 95763488.0}, "geometry": {"type": "Point", "coordinates": [2.5, 49.0]}, "record_timestamp": "2021-02-14T12:00:00+00:00"}, {"datasetid": "arpege-05-sp1_sp2", "recordid": "arpege_05_sp1_sp2_lastgrib20-2125651", "fields": {"2_metre_dewpoint_temperature": 5.500635000000045, "downward_short_wave_radiation_flux": 15679488.0, "2_metre_temperature": 7.761316000000022, "dist": "19256.4557757", "temperature": 7.125940000000014, "minimum_temperature_at_2_metres": 6.814539000000025, "timestamp": "2021-02-14T12:00:00+00:00", "v_component_of_wind_gust": 6.545319, "total_water_precipitation": 12.742188, "relative_humidity": 85.573685, "u_component_of_wind_gust": 10.761765, "wind_speed_gust": 12.59719, "position": [49.0, 2.5], "forecast": "2021-02-18T09:00:00+00:00", "maximum_temperature_at_2_metres": 8.184412000000009, "total_cloud_cover": 0.0, "downward_long_wave_radiation_flux": 102793296.0}, "geometry": {"type": "Point", "coordinates": [2.5, 49.0]}, "record_timestamp": "2021-02-14T12:00:00+00:00"}, {"datasetid": "arpege-05-sp1_sp2", "recordid": "arpege_05_sp1_sp2_lastgrib20-2125593", "fields": {"2_metre_dewpoint_temperature": 3.430688000000032, "downward_short_wave_radiation_flux": 4630528.0, "2_metre_temperature": 4.368188000000032, "dist": "30271.5658308", "temperature": 3.760400000000004, "minimum_temperature_at_2_metres": 3.596765000000005, "timestamp": "2021-02-14T12:00:00+00:00", "v_component_of_wind_gust": 8.007065, "total_water_precipitation": 3.382813, "relative_humidity": 93.760086, "u_component_of_wind_gust": 2.811829, "wind_speed_gust": 8.485979, "position": [49.0, 2.0], "forecast": "2021-02-15T15:00:00+00:00", "maximum_temperature_at_2_metres": 4.6508420000000115, "total_cloud_cover": 100.0, "downward_long_wave_radiation_flux": 29384152.0}, "geometry": {"type": "Point", "coordinates": [2.0, 49.0]}, "record_timestamp": "2021-02-14T12:00:00+00:00"}, {"datasetid": "arpege-05-sp1_sp2", "recordid": "arpege_05_sp1_sp2_lastgrib20-2125598", "fields": {"2_metre_dewpoint_temperature": 1.8197880000000168, "downward_short_wave_radiation_flux": 4851712.0, "2_metre_temperature": 3.1390930000000026, "dist": "30271.5658308", "temperature": 1.637537000000009, "minimum_temperature_at_2_metres": 1.6684810000000425, "timestamp": "2021-02-14T12:00:00+00:00", "v_component_of_wind_gust": 8.389526, "total_water_precipitation": 5.34375, "relative_humidity": 91.000061, "u_component_of_wind_gust": 2.680527, "wind_speed_gust": 8.801111, "position": [49.0, 2.0], "forecast": "2021-02-16T06:00:00+00:00", "maximum_temperature_at_2_metres": 3.1351870000000304, "total_cloud_cover": 100.0, "downward_long_wave_radiation_flux": 45240784.0}, "geometry": {"type": "Point", "coordinates": [2.0, 49.0]}, "record_timestamp": "2021-02-14T12:00:00+00:00"}, {"datasetid": "arpege-05-sp1_sp2", "recordid": "arpege_05_sp1_sp2_lastgrib20-2125600", "fields": {"2_metre_dewpoint_temperature": 5.212549000000024, "downward_short_wave_radiation_flux": 8296448.0, "2_metre_temperature": 6.7593930000000455, "dist": "30271.5658308", "temperature": 7.326775999999995, "minimum_temperature_at_2_metres": 3.451440000000048, "timestamp": "2021-02-14T12:00:00+00:00", "v_component_of_wind_gust": 8.077896, "total_water_precipitation": 5.339844, "relative_humidity": 89.883804, "u_component_of_wind_gust": 2.192642, "wind_speed_gust": 8.370047, "position": [49.0, 2.0], "forecast": "2021-02-16T12:00:00+00:00", "maximum_temperature_at_2_metres": 6.750878999999998, "total_cloud_cover": 100.0, "downward_long_wave_radiation_flux": 51325428.0}, "geometry": {"type": "Point", "coordinates": [2.0, 49.0]}, "record_timestamp": "2021-02-14T12:00:00+00:00"}, {"datasetid": "arpege-05-sp1_sp2", "recordid": "arpege_05_sp1_sp2_lastgrib20-2125610", "fields": {"2_metre_dewpoint_temperature": 6.763818000000015, "downward_short_wave_radiation_flux": 14440448.0, "2_metre_temperature": 8.204553000000033, "dist": "30271.5658308", "temperature": 6.8939150000000495, "minimum_temperature_at_2_metres": 8.229944000000046, "timestamp": "2021-02-14T12:00:00+00:00", "v_component_of_wind_gust": 10.219604, "total_water_precipitation": 6.570313, "relative_humidity": 90.632179, "u_component_of_wind_gust": 2.794464, "wind_speed_gust": 10.580308, "position": [49.0, 2.0], "forecast": "2021-02-17T18:00:00+00:00", "maximum_temperature_at_2_metres": 9.185204999999996, "total_cloud_cover": 100.0, "downward_long_wave_radiation_flux": 86906224.0}, "geometry": {"type": "Point", "coordinates": [2.0, 49.0]}, "record_timestamp": "2021-02-14T12:00:00+00:00"}, {"datasetid": "arpege-05-sp1_sp2", "recordid": "arpege_05_sp1_sp2_lastgrib20-2125589", "fields": {"2_metre_dewpoint_temperature": 0.34731400000003987, "downward_short_wave_radiation_flux": 2529280.0, "2_metre_temperature": 1.9537600000000452, "dist": "30271.5658308", "temperature": 0.7968380000000366, "minimum_temperature_at_2_metres": 0.397119000000032, "timestamp": "2021-02-14T12:00:00+00:00", "v_component_of_wind_gust": 7.693054, "total_water_precipitation": 0.341797, "relative_humidity": 89.121323, "u_component_of_wind_gust": -1.196594, "wind_speed_gust": 7.788101, "position": [49.0, 2.0], "forecast": "2021-02-15T03:00:00+00:00", "maximum_temperature_at_2_metres": 1.9495180000000119, "total_cloud_cover": 100.0, "downward_long_wave_radiation_flux": 15413015.0}, "geometry": {"type": "Point", "coordinates": [2.0, 49.0]}, "record_timestamp": "2021-02-14T12:00:00+00:00"}, {"datasetid": "arpege-05-sp1_sp2", "recordid": "arpege_05_sp1_sp2_lastgrib20-2125595", "fields": {"2_metre_dewpoint_temperature": 2.935999000000038, "downward_short_wave_radiation_flux": 4851712.0, "2_metre_temperature": 3.6492250000000013, "dist": "30271.5658308", "temperature": 2.4004150000000095, "minimum_temperature_at_2_metres": 3.6336000000000013, "timestamp": "2021-02-14T12:00:00+00:00", "v_component_of_wind_gust": 5.74707, "total_water_precipitation": 5.34375, "relative_humidity": 95.045166, "u_component_of_wind_gust": 2.900253, "wind_speed_gust": 6.447075, "position": [49.0, 2.0], "forecast": "2021-02-15T21:00:00+00:00", "maximum_temperature_at_2_metres": 4.04329800000005, "total_cloud_cover": 99.0, "downward_long_wave_radiation_flux": 36370088.0}, "geometry": {"type": "Point", "coordinates": [2.0, 49.0]}, "record_timestamp": "2021-02-14T12:00:00+00:00"}, {"datasetid": "arpege-05-sp1_sp2", "recordid": "arpege_05_sp1_sp2_lastgrib20-2125601", "fields": {"2_metre_dewpoint_temperature": 6.0775090000000205, "downward_short_wave_radiation_flux": 9883648.0, "2_metre_temperature": 7.232996000000014, "dist": "30271.5658308", "temperature": 6.4851620000000025, "minimum_temperature_at_2_metres": 6.828638000000012, "timestamp": "2021-02-14T12:00:00+00:00", "v_component_of_wind_gust": 7.295654, "total_water_precipitation": 5.34375, "relative_humidity": 92.536293, "u_component_of_wind_gust": 4.137299, "wind_speed_gust": 8.393877, "position": [49.0, 2.0], "forecast": "2021-02-16T15:00:00+00:00", "maximum_temperature_at_2_metres": 7.405603000000042, "total_cloud_cover": 100.0, "downward_long_wave_radiation_flux": 54755144.0}, "geometry": {"type": "Point", "coordinates": [2.0, 49.0]}, "record_timestamp": "2021-02-14T12:00:00+00:00"}, {"datasetid": "arpege-05-sp1_sp2", "recordid": "arpege_05_sp1_sp2_lastgrib20-2125607", "fields": {"2_metre_dewpoint_temperature": 5.771326000000045, "downward_short_wave_radiation_flux": 10133504.0, "2_metre_temperature": 6.446069000000023, "dist": "30271.5658308", "temperature": 5.944727, "minimum_temperature_at_2_metres": 4.834100000000035, "timestamp": "2021-02-14T12:00:00+00:00", "v_component_of_wind_gust": 9.318527, "total_water_precipitation": 6.570313, "relative_humidity": 95.490311, "u_component_of_wind_gust": 4.478622, "wind_speed_gust": 10.34339, "position": [49.0, 2.0], "forecast": "2021-02-17T09:00:00+00:00", "maximum_temperature_at_2_metres": 6.433252000000039, "total_cloud_cover": 100.0, "downward_long_wave_radiation_flux": 76539968.0}, "geometry": {"type": "Point", "coordinates": [2.0, 49.0]}, "record_timestamp": "2021-02-14T12:00:00+00:00"}, {"datasetid": "arpege-05-sp1_sp2", "recordid": "arpege_05_sp1_sp2_lastgrib20-2125612", "fields": {"2_metre_dewpoint_temperature": 6.948082999999997, "downward_short_wave_radiation_flux": 14438400.0, "2_metre_temperature": 8.24410400000005, "dist": "30271.5658308", "temperature": 7.233545000000049, "timestamp": "2021-02-14T12:00:00+00:00", "v_component_of_wind_gust": 12.397919, "total_water_precipitation": 6.601563, "relative_humidity": 91.645798, "u_component_of_wind_gust": 0.832733, "wind_speed_gust": 12.426527, "position": [49.0, 2.0], "forecast": "2021-02-18T00:00:00+00:00", "downward_long_wave_radiation_flux": 93423104.0, "total_cloud_cover": 100.0}, "geometry": {"type": "Point", "coordinates": [2.0, 49.0]}, "record_timestamp": "2021-02-14T12:00:00+00:00"}, {"datasetid": "arpege-05-sp1_sp2", "recordid": "arpege_05_sp1_sp2_lastgrib20-2125613", "fields": {"2_metre_dewpoint_temperature": 6.933130000000006, "downward_short_wave_radiation_flux": 14438400.0, "2_metre_temperature": 7.80159900000001, "dist": "30271.5658308", "temperature": 6.913110000000017, "minimum_temperature_at_2_metres": 7.571252000000015, "timestamp": "2021-02-14T12:00:00+00:00", "v_component_of_wind_gust": 12.06076, "total_water_precipitation": 7.421875, "relative_humidity": 94.240059, "u_component_of_wind_gust": 0.571793, "wind_speed_gust": 12.068514, "position": [49.0, 2.0], "forecast": "2021-02-18T03:00:00+00:00", "maximum_temperature_at_2_metres": 8.589197000000013, "total_cloud_cover": 100.0, "downward_long_wave_radiation_flux": 96975904.0}, "geometry": {"type": "Point", "coordinates": [2.0, 49.0]}, "record_timestamp": "2021-02-14T12:00:00+00:00"}, {"datasetid": "arpege-05-sp1_sp2", "recordid": "arpege_05_sp1_sp2_lastgrib20-2125615", "fields": {"2_metre_dewpoint_temperature": 4.969385000000045, "downward_short_wave_radiation_flux": 15081472.0, "2_metre_temperature": 7.323816000000022, "dist": "30271.5658308", "temperature": 6.625940000000014, "minimum_temperature_at_2_metres": 7.2266480000000115, "timestamp": "2021-02-14T12:00:00+00:00", "v_component_of_wind_gust": 8.795319, "total_water_precipitation": 8.976563, "relative_humidity": 84.854935, "u_component_of_wind_gust": 10.574265, "wind_speed_gust": 13.75344, "position": [49.0, 2.0], "forecast": "2021-02-18T09:00:00+00:00", "maximum_temperature_at_2_metres": 8.510582999999997, "total_cloud_cover": 0.0, "downward_long_wave_radiation_flux": 103843920.0}, "geometry": {"type": "Point", "coordinates": [2.0, 49.0]}, "record_timestamp": "2021-02-14T12:00:00+00:00"}, {"datasetid": "arpege-05-sp1_sp2", "recordid": "arpege_05_sp1_sp2_lastgrib20-2125604", "fields": {"2_metre_dewpoint_temperature": 5.570763999999997, "downward_short_wave_radiation_flux": 9943040.0, "2_metre_temperature": 5.766382000000021, "dist": "30271.5658308", "temperature": 5.201868000000047, "minimum_temperature_at_2_metres": 5.558954000000028, "timestamp": "2021-02-14T12:00:00+00:00", "v_component_of_wind_gust": 4.910904, "total_water_precipitation": 6.460938, "relative_humidity": 98.677155, "u_component_of_wind_gust": 6.961288, "wind_speed_gust": 8.514694, "position": [49.0, 2.0], "forecast": "2021-02-17T00:00:00+00:00", "maximum_temperature_at_2_metres": 5.774194000000023, "total_cloud_cover": 100.0, "downward_long_wave_radiation_flux": 65661728.0}, "geometry": {"type": "Point", "coordinates": [2.0, 49.0]}, "record_timestamp": "2021-02-14T12:00:00+00:00"}, {"datasetid": "arpege-05-sp1_sp2", "recordid": "arpege_05_sp1_sp2_lastgrib20-2125588", "fields": {"2_metre_dewpoint_temperature": -2.168920999999955, "downward_short_wave_radiation_flux": 2529280.0, "2_metre_temperature": -0.1593379999999911, "dist": "30271.5658308", "temperature": -0.6045899999999733, "minimum_temperature_at_2_metres": -0.21793199999996204, "timestamp": "2021-02-14T12:00:00+00:00", "v_component_of_wind_gust": 3.884644, "total_water_precipitation": 0.044922, "relative_humidity": 84.755867, "u_component_of_wind_gust": -4.352341, "wind_speed_gust": 5.836257, "position": [49.0, 2.0], "forecast": "2021-02-15T00:00:00+00:00", "maximum_temperature_at_2_metres": -0.08011499999997795, "total_cloud_cover": 100.0, "downward_long_wave_radiation_flux": 12002546.0}, "geometry": {"type": "Point", "coordinates": [2.0, 49.0]}, "record_timestamp": "2021-02-14T12:00:00+00:00"}, {"datasetid": "arpege-05-sp1_sp2", "recordid": "arpege_05_sp1_sp2_lastgrib20-2125591", "fields": {"2_metre_dewpoint_temperature": 1.1538020000000415, "downward_short_wave_radiation_flux": 2652160.0, "2_metre_temperature": 2.718530000000044, "dist": "30271.5658308", "temperature": 1.9173830000000294, "minimum_temperature_at_2_metres": 2.52883300000002, "timestamp": "2021-02-14T12:00:00+00:00", "v_component_of_wind_gust": 8.738708, "total_water_precipitation": 1.230469, "relative_humidity": 89.324608, "u_component_of_wind_gust": 2.941467, "wind_speed_gust": 9.209369, "position": [49.0, 2.0], "forecast": "2021-02-15T09:00:00+00:00", "maximum_temperature_at_2_metres": 2.817651000000012, "total_cloud_cover": 99.5, "downward_long_wave_radiation_flux": 22333290.0}, "geometry": {"type": "Point", "coordinates": [2.0, 49.0]}, "record_timestamp": "2021-02-14T12:00:00+00:00"}, {"datasetid": "arpege-05-sp1_sp2", "recordid": "arpege_05_sp1_sp2_lastgrib20-2125599", "fields": {"2_metre_dewpoint_temperature": 2.4349300000000085, "downward_short_wave_radiation_flux": 5236736.0, "2_metre_temperature": 3.466852000000017, "dist": "30271.5658308", "temperature": 2.7848749999999995, "minimum_temperature_at_2_metres": 2.7622010000000046, "timestamp": "2021-02-14T12:00:00+00:00", "v_component_of_wind_gust": 7.657364, "total_water_precipitation": 5.34375, "relative_humidity": 93.015457, "u_component_of_wind_gust": 2.783142, "wind_speed_gust": 8.152263, "position": [49.0, 2.0], "forecast": "2021-02-16T09:00:00+00:00", "maximum_temperature_at_2_metres": 3.462761999999998, "total_cloud_cover": 83.0, "downward_long_wave_radiation_flux": 48201232.0}, "geometry": {"type": "Point", "coordinates": [2.0, 49.0]}, "record_timestamp": "2021-02-14T12:00:00+00:00"}, {"datasetid": "arpege-05-sp1_sp2", "recordid": "arpege_05_sp1_sp2_lastgrib20-2125587", "fields": {"2_metre_dewpoint_temperature": -2.645879999999977, "downward_short_wave_radiation_flux": 2529280.0, "2_metre_temperature": -0.14041699999995672, "dist": "30271.5658308", "temperature": -0.7933409999999981, "minimum_temperature_at_2_metres": -0.6367549999999937, "timestamp": "2021-02-14T12:00:00+00:00", "v_component_of_wind_gust": 5.153687, "total_water_precipitation": 0.001953, "relative_humidity": 81.334633, "u_component_of_wind_gust": -5.210617, "wind_speed_gust": 7.326058, "position": [49.0, 2.0], "forecast": "2021-02-14T21:00:00+00:00", "maximum_temperature_at_2_metres": -0.14249300000000176, "total_cloud_cover": 99.0, "downward_long_wave_radiation_flux": 8856447.0}, "geometry": {"type": "Point", "coordinates": [2.0, 49.0]}, "record_timestamp": "2021-02-14T12:00:00+00:00"}, {"datasetid": "arpege-05-sp1_sp2", "recordid": "arpege_05_sp1_sp2_lastgrib20-2125603", "fields": {"2_metre_dewpoint_temperature": 5.418512000000021, "downward_short_wave_radiation_flux": 9943040.0, "2_metre_temperature": 5.649438000000032, "dist": "30271.5658308", "temperature": 4.997369000000049, "minimum_temperature_at_2_metres": 5.646539000000018, "timestamp": "2021-02-14T12:00:00+00:00", "v_component_of_wind_gust": 4.945938, "total_water_precipitation": 6.425781, "relative_humidity": 98.450607, "u_component_of_wind_gust": 6.490509, "wind_speed_gust": 8.17815, "position": [49.0, 2.0], "forecast": "2021-02-16T21:00:00+00:00", "maximum_temperature_at_2_metres": 6.38543100000004, "total_cloud_cover": 98.0, "downward_long_wave_radiation_flux": 61992000.0}, "geometry": {"type": "Point", "coordinates": [2.0, 49.0]}, "record_timestamp": "2021-02-14T12:00:00+00:00"}, {"datasetid": "arpege-05-sp1_sp2", "recordid": "arpege_05_sp1_sp2_lastgrib20-2125606", "fields": {"2_metre_dewpoint_temperature": 4.982141000000013, "downward_short_wave_radiation_flux": 9943040.0, "2_metre_temperature": 5.348657000000003, "dist": "30271.5658308", "temperature": 4.797021000000029, "minimum_temperature_at_2_metres": 5.369226000000026, "timestamp": "2021-02-14T12:00:00+00:00", "v_component_of_wind_gust": 7.602264, "total_water_precipitation": 6.523438, "relative_humidity": 97.415092, "u_component_of_wind_gust": 1.780487, "wind_speed_gust": 7.807074, "position": [49.0, 2.0], "forecast": "2021-02-17T06:00:00+00:00", "maximum_temperature_at_2_metres": 6.160059000000047, "total_cloud_cover": 88.5, "downward_long_wave_radiation_flux": 72978016.0}, "geometry": {"type": "Point", "coordinates": [2.0, 49.0]}, "record_timestamp": "2021-02-14T12:00:00+00:00"}, {"datasetid": "arpege-05-sp1_sp2", "recordid": "arpege_05_sp1_sp2_lastgrib20-2125608", "fields": {"2_metre_dewpoint_temperature": 6.598657000000003, "downward_short_wave_radiation_flux": 11780096.0, "2_metre_temperature": 7.811273000000028, "dist": "30271.5658308", "temperature": 7.722620000000006, "minimum_temperature_at_2_metres": 6.44768700000003, "timestamp": "2021-02-14T12:00:00+00:00", "v_component_of_wind_gust": 11.502777, "total_water_precipitation": 6.570313, "relative_humidity": 92.131012, "u_component_of_wind_gust": 5.890884, "wind_speed_gust": 12.929434, "position": [49.0, 2.0], "forecast": "2021-02-17T12:00:00+00:00", "maximum_temperature_at_2_metres": 7.820154000000002, "total_cloud_cover": 99.5, "downward_long_wave_radiation_flux": 80203008.0}, "geometry": {"type": "Point", "coordinates": [2.0, 49.0]}, "record_timestamp": "2021-02-14T12:00:00+00:00"}, {"datasetid": "arpege-05-sp1_sp2", "recordid": "arpege_05_sp1_sp2_lastgrib20-2125618", "fields": {"2_metre_dewpoint_temperature": 5.501824999999997, "downward_short_wave_radiation_flux": 20709376.0, "2_metre_temperature": 6.741663000000017, "dist": "30271.5658308", "temperature": 5.917871000000048, "minimum_temperature_at_2_metres": 6.457330000000013, "timestamp": "2021-02-14T12:00:00+00:00", "v_component_of_wind_gust": 16.711151, "total_water_precipitation": 11.914063, "relative_humidity": 91.840302, "u_component_of_wind_gust": 3.161743, "wind_speed_gust": 17.005264, "position": [49.0, 2.0], "forecast": "2021-02-19T00:00:00+00:00", "maximum_temperature_at_2_metres": 9.684106000000043, "total_cloud_cover": 100.0, "downward_long_wave_radiation_flux": 120266192.0}, "geometry": {"type": "Point", "coordinates": [2.0, 49.0]}, "record_timestamp": "2021-02-14T12:00:00+00:00"}, {"datasetid": "arpege-05-sp1_sp2", "recordid": "arpege_05_sp1_sp2_lastgrib20-2125590", "fields": {"2_metre_dewpoint_temperature": 1.5189150000000495, "downward_short_wave_radiation_flux": 2529280.0, "2_metre_temperature": 2.8053220000000465, "dist": "30271.5658308", "temperature": 1.9768310000000042, "minimum_temperature_at_2_metres": 1.2254880000000412, "timestamp": "2021-02-14T12:00:00+00:00", "v_component_of_wind_gust": 8.052856, "total_water_precipitation": 0.894531, "relative_humidity": 91.268959, "u_component_of_wind_gust": 1.87532, "wind_speed_gust": 8.267852, "position": [49.0, 2.0], "forecast": "2021-02-15T06:00:00+00:00", "maximum_temperature_at_2_metres": 2.8044680000000426, "total_cloud_cover": 100.0, "downward_long_wave_radiation_flux": 18934504.0}, "geometry": {"type": "Point", "coordinates": [2.0, 49.0]}, "record_timestamp": "2021-02-14T12:00:00+00:00"}, {"datasetid": "arpege-05-sp1_sp2", "recordid": "arpege_05_sp1_sp2_lastgrib20-2125594", "fields": {"2_metre_dewpoint_temperature": 3.115746999999999, "downward_short_wave_radiation_flux": 4851712.0, "2_metre_temperature": 3.8656860000000393, "dist": "30271.5658308", "temperature": 3.0663090000000466, "minimum_temperature_at_2_metres": 3.8695920000000115, "timestamp": "2021-02-14T12:00:00+00:00", "v_component_of_wind_gust": 5.537399, "total_water_precipitation": 3.9375, "relative_humidity": 94.83992, "u_component_of_wind_gust": 2.097763, "wind_speed_gust": 5.930498, "position": [49.0, 2.0], "forecast": "2021-02-15T18:00:00+00:00", "maximum_temperature_at_2_metres": 4.326807000000031, "total_cloud_cover": 100.0, "downward_long_wave_radiation_flux": 32943410.0}, "geometry": {"type": "Point", "coordinates": [2.0, 49.0]}, "record_timestamp": "2021-02-14T12:00:00+00:00"}, {"datasetid": "arpege-05-sp1_sp2", "recordid": "arpege_05_sp1_sp2_lastgrib20-2125597", "fields": {"2_metre_dewpoint_temperature": 1.2556090000000495, "downward_short_wave_radiation_flux": 4851712.0, "2_metre_temperature": 1.7061400000000049, "dist": "30271.5658308", "temperature": 0.2007080000000201, "minimum_temperature_at_2_metres": 1.7173099999999977, "timestamp": "2021-02-14T12:00:00+00:00", "v_component_of_wind_gust": 5.806168, "total_water_precipitation": 5.339844, "relative_humidity": 96.811523, "u_component_of_wind_gust": -0.853485, "wind_speed_gust": 5.856687, "position": [49.0, 2.0], "forecast": "2021-02-16T03:00:00+00:00", "maximum_temperature_at_2_metres": 3.1924680000000194, "total_cloud_cover": 71.5, "downward_long_wave_radiation_flux": 42285800.0}, "geometry": {"type": "Point", "coordinates": [2.0, 49.0]}, "record_timestamp": "2021-02-14T12:00:00+00:00"}, {"datasetid": "arpege-05-sp1_sp2", "recordid": "arpege_05_sp1_sp2_lastgrib20-2125605", "fields": {"2_metre_dewpoint_temperature": 5.605737000000033, "downward_short_wave_radiation_flux": 9943040.0, "2_metre_temperature": 6.102350000000001, "dist": "30271.5658308", "temperature": 5.373010000000022, "minimum_temperature_at_2_metres": 5.749597000000051, "timestamp": "2021-02-14T12:00:00+00:00", "v_component_of_wind_gust": 5.285431, "total_water_precipitation": 6.5, "relative_humidity": 96.581833, "u_component_of_wind_gust": 6.013443, "wind_speed_gust": 7.996695, "position": [49.0, 2.0], "forecast": "2021-02-17T03:00:00+00:00", "maximum_temperature_at_2_metres": 6.121210000000019, "total_cloud_cover": 100.0, "downward_long_wave_radiation_flux": 69358560.0}, "geometry": {"type": "Point", "coordinates": [2.0, 49.0]}, "record_timestamp": "2021-02-14T12:00:00+00:00"}, {"datasetid": "arpege-05-sp1_sp2", "recordid": "arpege_05_sp1_sp2_lastgrib20-2125609", "fields": {"2_metre_dewpoint_temperature": 6.8629999999999995, "downward_short_wave_radiation_flux": 13940736.0, "2_metre_temperature": 9.141107000000034, "dist": "30271.5658308", "temperature": 8.480737000000033, "minimum_temperature_at_2_metres": 7.859888000000012, "timestamp": "2021-02-14T12:00:00+00:00", "v_component_of_wind_gust": 11.161621, "total_water_precipitation": 6.570313, "relative_humidity": 85.621445, "u_component_of_wind_gust": 5.989014, "wind_speed_gust": 12.662103, "position": [49.0, 2.0], "forecast": "2021-02-17T15:00:00+00:00", "maximum_temperature_at_2_metres": 9.187219000000027, "total_cloud_cover": 100.0, "downward_long_wave_radiation_flux": 83729120.0}, "geometry": {"type": "Point", "coordinates": [2.0, 49.0]}, "record_timestamp": "2021-02-14T12:00:00+00:00"}, {"datasetid": "arpege-05-sp1_sp2", "recordid": "arpege_05_sp1_sp2_lastgrib20-2125611", "fields": {"2_metre_dewpoint_temperature": 6.502893000000029, "downward_short_wave_radiation_flux": 14438400.0, "2_metre_temperature": 8.524347000000034, "dist": "30271.5658308", "temperature": 7.100366000000008, "minimum_temperature_at_2_metres": 8.086815999999999, "timestamp": "2021-02-14T12:00:00+00:00", "v_component_of_wind_gust": 13.073883, "total_water_precipitation": 6.578125, "relative_humidity": 87.081932, "u_component_of_wind_gust": 1.096817, "wind_speed_gust": 13.125729, "position": [49.0, 2.0], "forecast": "2021-02-17T21:00:00+00:00", "maximum_temperature_at_2_metres": 8.50716600000004, "total_cloud_cover": 100.0, "downward_long_wave_radiation_flux": 90095824.0}, "geometry": {"type": "Point", "coordinates": [2.0, 49.0]}, "record_timestamp": "2021-02-14T12:00:00+00:00"}, {"datasetid": "arpege-05-sp1_sp2", "recordid": "arpege_05_sp1_sp2_lastgrib20-2125616", "fields": {"2_metre_dewpoint_temperature": 5.084741000000008, "downward_short_wave_radiation_flux": 17690624.0, "2_metre_temperature": 8.149133000000006, "dist": "30271.5658308", "temperature": 7.212061000000006, "minimum_temperature_at_2_metres": 7.347101000000009, "timestamp": "2021-02-14T12:00:00+00:00", "v_component_of_wind_gust": 11.173599, "total_water_precipitation": 9.140625, "relative_humidity": 81.014084, "u_component_of_wind_gust": 14.038345, "wind_speed_gust": 17.928179, "position": [49.0, 2.0], "forecast": "2021-02-18T12:00:00+00:00", "maximum_temperature_at_2_metres": 8.629175000000032, "total_cloud_cover": 53.0, "downward_long_wave_radiation_flux": 107010592.0}, "geometry": {"type": "Point", "coordinates": [2.0, 49.0]}, "record_timestamp": "2021-02-14T12:00:00+00:00"}, {"datasetid": "arpege-05-sp1_sp2", "recordid": "arpege_05_sp1_sp2_lastgrib20-2125617", "fields": {"2_metre_dewpoint_temperature": 5.3364500000000135, "downward_short_wave_radiation_flux": 20709376.0, "2_metre_temperature": 8.119592000000011, "dist": "30271.5658308", "temperature": 6.774315999999999, "minimum_temperature_at_2_metres": 7.320154000000002, "timestamp": "2021-02-14T12:00:00+00:00", "v_component_of_wind_gust": 9.376022, "total_water_precipitation": 9.78125, "relative_humidity": 82.546776, "u_component_of_wind_gust": 8.318649, "wind_speed_gust": 12.543506, "position": [49.0, 2.0], "forecast": "2021-02-18T18:00:00+00:00", "maximum_temperature_at_2_metres": 9.686121000000014, "total_cloud_cover": 100.0, "downward_long_wave_radiation_flux": 113606000.0}, "geometry": {"type": "Point", "coordinates": [2.0, 49.0]}, "record_timestamp": "2021-02-14T12:00:00+00:00"}, {"datasetid": "arpege-05-sp1_sp2", "recordid": "arpege_05_sp1_sp2_lastgrib20-2125619", "fields": {"2_metre_dewpoint_temperature": 8.957605000000001, "downward_short_wave_radiation_flux": 20709376.0, "2_metre_temperature": 9.650079000000005, "dist": "30271.5658308", "temperature": 8.895258000000013, "minimum_temperature_at_2_metres": 6.394800000000032, "timestamp": "2021-02-14T12:00:00+00:00", "v_component_of_wind_gust": 13.899948, "total_water_precipitation": 13.515625, "relative_humidity": 95.546371, "u_component_of_wind_gust": 8.368805, "wind_speed_gust": 16.224983, "position": [49.0, 2.0], "forecast": "2021-02-19T06:00:00+00:00", "maximum_temperature_at_2_metres": 9.635095000000035, "total_cloud_cover": 100.0, "downward_long_wave_radiation_flux": 127799632.0}, "geometry": {"type": "Point", "coordinates": [2.0, 49.0]}, "record_timestamp": "2021-02-14T12:00:00+00:00"}, {"datasetid": "arpege-05-sp1_sp2", "recordid": "arpege_05_sp1_sp2_lastgrib20-2125584", "fields": {"2_metre_dewpoint_temperature": -7.694249999999954, "2_metre_temperature": -1.3169919999999706, "dist": "30271.5658308", "temperature": 1.4671260000000075, "timestamp": "2021-02-14T12:00:00+00:00", "forecast": "2021-02-14T12:00:00+00:00", "relative_humidity": 58.126064, "position": [49.0, 2.0], "total_cloud_cover": 100.0}, "geometry": {"type": "Point", "coordinates": [2.0, 49.0]}, "record_timestamp": "2021-02-14T12:00:00+00:00"}, {"datasetid": "arpege-05-sp1_sp2", "recordid": "arpege_05_sp1_sp2_lastgrib20-2125585", "fields": {"2_metre_dewpoint_temperature": -5.071935999999994, "downward_short_wave_radiation_flux": 2322944.0, "2_metre_temperature": -0.1766719999999964, "dist": "30271.5658308", "temperature": 0.05513899999999694, "minimum_temperature_at_2_metres": -1.358556999999962, "timestamp": "2021-02-14T12:00:00+00:00", "v_component_of_wind_gust": 5.322342, "total_water_precipitation": 0.0, "relative_humidity": 66.34626, "u_component_of_wind_gust": -7.217377, "wind_speed_gust": 8.977092, "position": [49.0, 2.0], "forecast": "2021-02-14T15:00:00+00:00", "maximum_temperature_at_2_metres": -0.1742919999999799, "total_cloud_cover": 100.0, "downward_long_wave_radiation_flux": 2883086.25}, "geometry": {"type": "Point", "coordinates": [2.0, 49.0]}, "record_timestamp": "2021-02-14T12:00:00+00:00"}, {"datasetid": "arpege-05-sp1_sp2", "recordid": "arpege_05_sp1_sp2_lastgrib20-2125586", "fields": {"2_metre_dewpoint_temperature": -3.5951599999999644, "downward_short_wave_radiation_flux": 2529792.0, "2_metre_temperature": -0.876989999999978, "dist": "30271.5658308", "temperature": -1.4426639999999793, "minimum_temperature_at_2_metres": -0.8758909999999673, "timestamp": "2021-02-14T12:00:00+00:00", "v_component_of_wind_gust": 4.297119, "total_water_precipitation": 0.001953, "relative_humidity": 79.519089, "u_component_of_wind_gust": -7.420593, "wind_speed_gust": 8.582509, "position": [49.0, 2.0], "forecast": "2021-02-14T18:00:00+00:00", "maximum_temperature_at_2_metres": -0.24890699999997423, "total_cloud_cover": 100.0, "downward_long_wave_radiation_flux": 5826450.0}, "geometry": {"type": "Point", "coordinates": [2.0, 49.0]}, "record_timestamp": "2021-02-14T12:00:00+00:00"}, {"datasetid": "arpege-05-sp1_sp2", "recordid": "arpege_05_sp1_sp2_lastgrib20-2125592", "fields": {"2_metre_dewpoint_temperature": 2.4655089999999973, "downward_short_wave_radiation_flux": 3524608.0, "2_metre_temperature": 3.608545000000049, "dist": "30271.5658308", "temperature": 3.4067019999999957, "minimum_temperature_at_2_metres": 2.7600950000000353, "timestamp": "2021-02-14T12:00:00+00:00", "v_component_of_wind_gust": 7.825775, "total_water_precipitation": 2.753906, "relative_humidity": 92.240303, "u_component_of_wind_gust": 3.975204, "wind_speed_gust": 8.76896, "position": [49.0, 2.0], "forecast": "2021-02-15T12:00:00+00:00", "maximum_temperature_at_2_metres": 3.6028380000000197, "total_cloud_cover": 99.5, "downward_long_wave_radiation_flux": 25805860.0}, "geometry": {"type": "Point", "coordinates": [2.0, 49.0]}, "record_timestamp": "2021-02-14T12:00:00+00:00"}, {"datasetid": "arpege-05-sp1_sp2", "recordid": "arpege_05_sp1_sp2_lastgrib20-2125596", "fields": {"2_metre_dewpoint_temperature": 2.526270000000011, "downward_short_wave_radiation_flux": 4851712.0, "2_metre_temperature": 3.1676270000000386, "dist": "30271.5658308", "temperature": 1.8042240000000334, "minimum_temperature_at_2_metres": 3.180383000000006, "timestamp": "2021-02-14T12:00:00+00:00", "v_component_of_wind_gust": 5.902359, "total_water_precipitation": 5.34375, "relative_humidity": 95.549225, "u_component_of_wind_gust": 2.770996, "wind_speed_gust": 6.52794, "position": [49.0, 2.0], "forecast": "2021-02-16T00:00:00+00:00", "maximum_temperature_at_2_metres": 3.7925350000000435, "total_cloud_cover": 87.5, "downward_long_wave_radiation_flux": 39494912.0}, "geometry": {"type": "Point", "coordinates": [2.0, 49.0]}, "record_timestamp": "2021-02-14T12:00:00+00:00"}, {"datasetid": "arpege-05-sp1_sp2", "recordid": "arpege_05_sp1_sp2_lastgrib20-2125602", "fields": {"2_metre_dewpoint_temperature": 5.959375000000023, "downward_short_wave_radiation_flux": 9940992.0, "2_metre_temperature": 6.405573000000004, "dist": "30271.5658308", "temperature": 5.563989000000049, "minimum_temperature_at_2_metres": 6.405573000000004, "timestamp": "2021-02-14T12:00:00+00:00", "v_component_of_wind_gust": 5.604324, "total_water_precipitation": 6.402344, "relative_humidity": 97.037918, "u_component_of_wind_gust": 4.684448, "wind_speed_gust": 7.304316, "position": [49.0, 2.0], "forecast": "2021-02-16T18:00:00+00:00", "maximum_temperature_at_2_metres": 7.206322999999998, "total_cloud_cover": 99.5, "downward_long_wave_radiation_flux": 58472716.0}, "geometry": {"type": "Point", "coordinates": [2.0, 49.0]}, "record_timestamp": "2021-02-14T12:00:00+00:00"}, {"datasetid": "arpege-05-sp1_sp2", "recordid": "arpege_05_sp1_sp2_lastgrib20-2125614", "fields": {"2_metre_dewpoint_temperature": 6.282007000000021, "downward_short_wave_radiation_flux": 14438400.0, "2_metre_temperature": 8.03457000000003, "dist": "30271.5658308", "temperature": 6.956079000000045, "minimum_temperature_at_2_metres": 7.481714000000011, "timestamp": "2021-02-14T12:00:00+00:00", "v_component_of_wind_gust": 12.466919, "total_water_precipitation": 8.546875, "relative_humidity": 88.605301, "u_component_of_wind_gust": 10.94722, "wind_speed_gust": 16.571039, "position": [49.0, 2.0], "forecast": "2021-02-18T06:00:00+00:00", "maximum_temperature_at_2_metres": 8.498804000000007, "total_cloud_cover": 100.0, "downward_long_wave_radiation_flux": 100621856.0}, "geometry": {"type": "Point", "coordinates": [2.0, 49.0]}, "record_timestamp": "2021-02-14T12:00:00+00:00"}], "facet_groups": [{"facets": [{"count": 72, "path": "2021", "state": "displayed", "name": "2021"}], "name": "forecast"}]}